[
  {
    "id": 1,
    "location": "대구광역시",
    "storeName": "룸즈에이 대구동성로점",
    "address": "대구광역시 중구 동성로6길 16",
    "phoneNumber": "0507-1389-3838",
    "homepage": "http://roomsa.co.kr/new_main.asp?R_JIJEM=S10",
    "image": "http://roomsa.co.kr/upload_file/thema/maintheme(15).jpg",
    "title": "취중진담",
    "genre": "감성/스토리",
    "difficulty": 4,
    "activity": 3,
    "horror": 1,
    "description": "이곳은 누군가의 과거로 가볼 수 있는 술집입니다. 칵테일 한 잔에 과거의 이야기를 알 수 있는 술집이라... 이곳을 찾은 손님들의 취중진담을 들어볼까요?",
    "recommendation": "몽글몽글한 감성 스토리를 좋아하시는 분"
  },
  {
    "id": 2,
    "location": "대구광역시",
    "storeName": "룸즈에이 대구동성로점",
    "address": "대구광역시 중구 동성로6길 16",
    "phoneNumber": "0507-1389-3838",
    "homepage": "http://roomsa.co.kr/new_main.asp?R_JIJEM=S10",
    "image": "http://roomsa.co.kr/upload_file/thema/maintheme(14).jpg",
    "title": "노블리스트",
    "genre": "스토리/스릴러",
    "difficulty": 4,
    "activity": 4,
    "horror": 3,
    "description": "만년 작가 지망생 ‘송설’은 어느 날 BOOKS A 출판사에서 진행한 <연구소> 출간기념 이벤트에 당첨되어 평소 동경하던 유명한 소설 작가인 ‘노블’과의 식사권을 얻게 된다. 설레는 마음으로 그녀는 그를 만나러 가는데...",
    "recommendation": "끝이 없이 이어지는 문제를 푸는 걸 즐기시는 분"
  },
  {
    "id": 3,
    "location": "대구광역시",
    "storeName": "룸즈에이 대구동성로점",
    "address": "대구광역시 중구 동성로6길 16",
    "phoneNumber": "0507-1389-3838",
    "homepage": "http://roomsa.co.kr/new_main.asp?R_JIJEM=S10",
    "image": "http://roomsa.co.kr/upload_file/thema/maintheme(7).jpg",
    "title": "뽀득뽀득",
    "genre": "큐트/목욕",
    "difficulty": 4,
    "activity": 3,
    "horror": 1,
    "description": "우리 아빠는 술만 마시면 맨날 목욕탕에 가자고 한다. 목욕은 정말 실다.",
    "recommendation": "인테리어 퀄리티를 깐깐히 따지시는 분"
  },
  {
    "id": 4,
    "location": "대구광역시",
    "storeName": "룸즈에이 대구동성로점",
    "address": "대구광역시 중구 동성로6길 16",
    "phoneNumber": "0507-1389-3838",
    "homepage": "http://roomsa.co.kr/new_main.asp?R_JIJEM=S10",
    "image": "http://roomsa.co.kr/upload_file/thema/maintheme(16).jpg",
    "title": "반짝반짝",
    "genre": "잠입/탈취",
    "difficulty": 4,
    "activity": 4,
    "horror": 2,
    "description": "반짝거리는 물건을 터는 대도. 오늘은 어떤 물건을 훔쳐볼까?",
    "recommendation": "꽤나 어려운 문제를 푸는 성취감을 느끼고 싶으신 분"
  },
  {
    "id": 5,
    "location": "대구광역시",
    "storeName": "룸즈에이 대구동성로점",
    "address": "대구광역시 중구 동성로6길 16",
    "phoneNumber": "0507-1389-3838",
    "homepage": "http://roomsa.co.kr/new_main.asp?R_JIJEM=S10",
    "image": "http://roomsa.co.kr/upload_file/thema/maintheme(17).jpg",
    "title": "아이돌 남친",
    "genre": "로맨스/스릴러",
    "difficulty": 4,
    "activity": 3,
    "horror": 3,
    "description": "내 사랑스러운 남자친구는 아이돌이다.",
    "recommendation": "무서운 거 싫어하고 많이 움직이지 않고 탈출하고 싶은신 분"
  },
  {
    "id": 6,
    "location": "대구광역시",
    "storeName": "룸즈에이 동성로2호점",
    "address": "대구광역시 중구 동성로2길 50-18",
    "phoneNumber": "0507-1340-3853",
    "homepage": "http://roomsa.co.kr/new_main.asp?R_JIJEM=S15&gotopage=",
    "image": "http://roomsa.co.kr/upload_file/thema/maintheme(24).jpg",
    "title": "띵가띵가",
    "genre": "큐트/코믹",
    "difficulty": 3,
    "activity": 4,
    "horror": 1,
    "description": "나는 맨날 빵점이다. 공부는 정말 실다.",
    "recommendation": "귀여운 걸 좋아하고 여러 방을 옮겨 다니는 게 재밌으신 분"
  },
  {
    "id": 7,
    "location": "대구광역시",
    "storeName": "룸즈에이 동성로2호점",
    "address": "대구광역시 중구 동성로2길 50-18",
    "phoneNumber": "0507-1340-3853",
    "homepage": "http://roomsa.co.kr/new_main.asp?R_JIJEM=S15&gotopage=",
    "image": "http://roomsa.co.kr/upload_file/thema/maintheme(22).jpg",
    "title": "아이덴티티",
    "genre": "첩보/코믹",
    "difficulty": 4,
    "activity": 3,
    "horror": 1,
    "description": "(활동성이 높아 치마 등의 복장은 불편하실 수 있으니 참고해주십시오.) 나 요원 D는 보스의 총애를 받는 귀염둥이 요원. 어느 날부턴가 보스가 나에게 어떠한 지령도 주지 않는 게 이상하다. 아무래도 보스를 찾아가 봐야 할 것 같다!",
    "recommendation": "미친 활동성! 버라이어티 예능에 출연한 느낌을 원하는 분"
  },
  {
    "id": 8,
    "location": "대구광역시",
    "storeName": "룸즈에이 동성로2호점",
    "address": "대구광역시 중구 동성로2길 50-18",
    "phoneNumber": "0507-1340-3853",
    "homepage": "http://roomsa.co.kr/new_main.asp?R_JIJEM=S15&gotopage=",
    "image": "http://roomsa.co.kr/upload_file/thema/maintheme(23).jpg",
    "title": "그레이스 호텔",
    "genre": "공포/스릴러",
    "difficulty": 4,
    "activity": 4,
    "horror": 4,
    "description": "- 야간 근무 직원 모집 (0명) - GRACE HOTEL에서 오래도록 일하실 직원을 구합니다. 많은 지원 바랍니다.",
    "recommendation": "공포 방탈출 입문용 테마를 찾으시는 분"
  },
  {
    "id": 9,
    "location": "대구광역시",
    "storeName": "룸즈에이 동성로2호점",
    "address": "대구광역시 중구 동성로2길 50-18",
    "phoneNumber": "0507-1340-3853",
    "homepage": "http://roomsa.co.kr/new_main.asp?R_JIJEM=S15&gotopage=",
    "image": "http://roomsa.co.kr/upload_file/thema/maintheme(23).jpg",
    "title": "커밍순",
    "genre": "스토리",
    "difficulty": 4,
    "activity": 2,
    "horror": 3,
    "description": "당신에게도 이루고 싶은 꿈이 있나요?",
    "recommendation": "하나하나 꼼꼼한 디테일을 좋아하시는 분"
  },
  {
    "id": 10,
    "location": "대구광역시",
    "storeName": "룸즈에이 동성로2호점",
    "address": "대구광역시 중구 동성로2길 50-18",
    "phoneNumber": "0507-1340-3853",
    "homepage": "http://roomsa.co.kr/new_main.asp?R_JIJEM=S15&gotopage=",
    "image": "http://roomsa.co.kr/upload_file/thema/웹용-포스터_여우골.jpg",
    "title": "여우골",
    "genre": "설화/괴담",
    "difficulty": 4,
    "activity": 3,
    "horror": 4,
    "description": "달도 빛을 잃어가던 어둑한 밤, 한양으로 행하던 중 한 고을에 도착하는데..",
    "recommendation": "어떤 단서도 허투루 보지 않는 관찰력이 좋으신 분"
  },
  {
    "id": 11,
    "location": "대구광역시",
    "storeName": "룸즈에이 동성로 아카데미점",
    "address": "대구광역시 중구 중앙대로 412-21",
    "phoneNumber": "0507-1302-4147",
    "homepage": "http://roomsa.co.kr/new_main.asp?R_JIJEM=S17&gotopage=",
    "image": "http://roomsa.co.kr/upload_file/thema/웹용-포스터_우당탕탕.jpg",
    "title": "우당탕탕",
    "genre": "큐트/으스스",
    "difficulty": 4,
    "activity": 3,
    "horror": 3,
    "description": "얌전히 있는 것은 너무 어려따.",
    "recommendation": "아기자기하고 어린아이 감성을 좋아하시는 분"
  },
  {
    "id": 12,
    "location": "대구광역시",
    "storeName": "룸즈에이 동성로 아카데미점",
    "address": "대구광역시 중구 중앙대로 412-21",
    "phoneNumber": "0507-1302-4147",
    "homepage": "http://roomsa.co.kr/new_main.asp?R_JIJEM=S17&gotopage=",
    "image": "http://roomsa.co.kr/upload_file/thema/maintheme(2).jpg",
    "title": "필활",
    "genre": "역사/잠입",
    "difficulty": 4,
    "activity": 4,
    "horror": 3,
    "description": "19세기 조선, 팔도에서 최고로 손꼽히는 민간 해결사로 유명했던 당신. 어느 날, 날벼락같이 들이닥친 포졸들에게 잡혀 궁 내의 감옥에 갇히게 된다. 무슨 죄로 잡혀온 지도 모르는 당신에게 한 통의 서신이 도착한다.",
    "recommendation": "끝 없이 새로 나오는 방과 많은 문제를 경험하고 싶으신 분"
  },
  {
    "id": 13,
    "location": "대구광역시",
    "storeName": "룸즈에이 동성로 아카데미점",
    "address": "대구광역시 중구 중앙대로 412-21",
    "phoneNumber": "0507-1302-4147",
    "homepage": "http://roomsa.co.kr/new_main.asp?R_JIJEM=S17&gotopage=",
    "image": "http://roomsa.co.kr/upload_file/thema/웹-포스터-변환용_에이마트.jpg",
    "title": "평화로운 에이마트",
    "genre": "미션/활동성",
    "difficulty": 4,
    "activity": 5,
    "horror": 1,
    "description": "오늘도 평화로운 에이마트. 정신없이 바쁜 하루를 잘 보낼 수 있을까?",
    "recommendation": "밝은 분위기, 유머러스한 테마에서 색다른 경험을 원하시는 분"
  },
  {
    "id": 14,
    "location": "대구광역시",
    "storeName": "룸즈에이 동성로 아카데미점",
    "address": "대구광역시 중구 중앙대로 412-21",
    "phoneNumber": "0507-1302-4147",
    "homepage": "http://roomsa.co.kr/new_main.asp?R_JIJEM=S17&gotopage=",
    "image": "http://roomsa.co.kr/upload_file/thema/웹용-포스터(1).jpg",
    "title": "명부에 점을 찍으라",
    "genre": "천만영화/시사회",
    "difficulty": 4,
    "activity": 3,
    "horror": 3,
    "description": "영화 같은 운명, 운명 같은 영화 이 영화는 27세의 한 천재, 그리고 운명에 관한 이야기입니다.",
    "recommendation": "갓찰력을 요구하는 문과형 문제를 좋아하시는 분"
  },
  {
    "id": 15,
    "location": "대구광역시",
    "storeName": "마스터키 동성로점",
    "address": "대구광역시 중구 동성로5길 62",
    "phoneNumber": "0507-1317-7503",
    "homepage": "http://www.master-key.co.kr/booking/bk_detail?bid=9",
    "image": "http://www.master-key.co.kr/upload/room/58_img1.jpg",
    "title": "천사와 악마",
    "genre": "추리",
    "difficulty": 5,
    "activity": 4,
    "horror": 4,
    "description": "​ 잘못된 믿음을 가진 천사의 악행\n서울대 종교기호학과 교수인 당신은 의문의 인물로 부터 신촌의 성지라 불리는 마스터 교회에서 수상한 의식이 행해진다는 소식을 들었다.\n몇년 전 부터 신도들이 하나둘씩 의문사 하거나 사라지는 사건들이 벌어졌는데, 이 사건과 관련이 있음을 밝혀달라는 내용이다. \n의문의 인물의 도움으로 교회안에 무사히 도착한 당신은 신부가 기도하러 돌아오기전까지 60분안에 비밀을 파헤쳐야 한다",
    "recommendation": "이건 진짜 교회가 아닌가? 저절로 몰입감을 주는 인테리어를 좋아하시는 분"
  },
  {
    "id": 16,
    "location": "대구광역시",
    "storeName": "마스터키 동성로점",
    "address": "대구광역시 중구 동성로5길 62",
    "phoneNumber": "0507-1317-7503",
    "homepage": "http://www.master-key.co.kr/booking/bk_detail?bid=9",
    "image": "http://www.master-key.co.kr/img/19_img.png",
    "title": "그레이 인 인셉션",
    "genre": "성인",
    "difficulty": 2,
    "activity": 3,
    "horror": 4,
    "description": "모든 것을 가진 젊은 CEO ‘크리스찬 그레이’, 그의 마력에 빠진 ‘아나스타샤’.\n순수한 사회 초년생인 ‘아나스타샤’는 마성적인 매력을 갖고 있는 ‘그레 이’의 모든 것을 알고 싶어지게 된다. \n그에게 다가갈수록 확실해지는 그의 숨겨진 취향, 그녀는 모든 것을 받아드리기로 마음을 먹으나, 그럴수 록 거부감이 생기는 그의 숨겨진 비밀. \n거부할수 없는 본능의 물결속에 자신의 가치관이 흔들리는 그녀. 자신의 가치관과 그를 놓치지 않기위해 그녀는 그의 꿈속으로 향해 들어가는데...",
    "recommendation": "성인…을 위한 장난감을 잔뜩 보고 싶은 커플"
  },
  {
    "id": 17,
    "location": "대구광역시",
    "storeName": "마스터키 동성로점",
    "address": "대구광역시 중구 동성로5길 62",
    "phoneNumber": "0507-1317-7503",
    "homepage": "http://www.master-key.co.kr/booking/bk_detail?bid=9",
    "image": "http://www.master-key.co.kr/upload/room/56_img1.jpg",
    "title": "13 여고괴담",
    "genre": "공포",
    "difficulty": 4,
    "activity": 3,
    "horror": 5,
    "description": "​ ​ ’13 클럽의 초대장’\n‘이 글을 읽는 당신은 B여고의 0학년 13반 13번 입니다. 13번이 된 당신은 매월 13일 사고를 당할 것입니다. 도움이 필요하면 연락주세요.’\n새학기 첫날부터 받은 수상한 메시지, 미신을 대수롭게 넘기는 나는 누군가의 장난으로 생각하였다.\n3월 13일, 미술실으로 이동하다가 계단에서 넘어졌다.\n4월 13일, 화단에서 떨어지는 화분에 사고를 당했다.\n연이은 사고에 학기초에 받은 메시지로 연락을 하였다.\n수화기넘어 들려오는 차분한 목소리, 그녀 또한 13번이었다. \n이유 없는 13반 13번의 사고, 다들 넘기는 분위기였지만, 감수성이 예민한 고등학생이기에 순식간에 13번은 저주의 아이콘이 되었다. 그녀는 끊임없는 괴롭힘을 견디며 13번에 대한 정보를 수집하였다. \n그리고 이 모든 시작은 13년전 어느날부터라는 걸 파악하였는데…",
    "recommendation": "처음으로 무서워서 옆구리가 땡겨보고 싶으신 분"
  },
  {
    "id": 18,
    "location": "대구광역시",
    "storeName": "마스터키 동성로점",
    "address": "대구광역시 중구 동성로5길 62",
    "phoneNumber": "0507-1317-7503",
    "homepage": "http://www.master-key.co.kr/booking/bk_detail?bid=9",
    "image": "http://www.master-key.co.kr/upload/room/54_img1.jpg",
    "title": "화이트룸",
    "genre": "퍼즐 추리",
    "difficulty": 5,
    "activity": 3,
    "horror": 5,
    "description": "눈을 떠보니.. 낯선곳이다.\n\"난 누구지? 왜 여기 있는거지?\"\n순간 불이 켜지면서 의문의 사람이 스크린에 보여진다.\n이곳을 탈출하게 도와준다고 하는데 믿음이 가지 않는다.\n하지만 방법이 없다.\n실루엣과 함께 이 하얀방을 탈출하자!",
    "recommendation": "이벤트로 챕터를 성공할 때마다 떨어지는 선물이 궁금하신 분"
  },
  {
    "id": 19,
    "location": "대구광역시",
    "storeName": "마스터키 동성로점",
    "address": "대구광역시 중구 동성로5길 62",
    "phoneNumber": "0507-1317-7503",
    "homepage": "http://www.master-key.co.kr/booking/bk_detail?bid=9",
    "image": "http://www.master-key.co.kr/upload/room/57_img1.jpg",
    "title": "드라큘라",
    "genre": "어드벤처 퍼즐",
    "difficulty": 2,
    "activity": 4,
    "horror": 5,
    "description": "골동품 수집하는게 취미인 당신은 먼지가 쌓인 물품 속에서 낡은 일지를 발견 하게된다.\n일지의 페이지 중 몇 장이 누락된 것을 알게 되자\n흥미를 느낀 당신은 반 헬싱의 흔적을 쫓아 드라큘라 고성으로 향하게 되는데. .",
    "recommendation": "매니아 보다는 초보 유저들"
  },
  {
    "id": 20,
    "location": "대구광역시",
    "storeName": "마스터키 동성로점",
    "address": "대구광역시 중구 동성로5길 62",
    "phoneNumber": "0507-1317-7503",
    "homepage": "http://www.master-key.co.kr/booking/bk_detail?bid=9",
    "image": "http://www.master-key.co.kr/upload/room/55_img1.jpg",
    "title": "인디아나 존스",
    "genre": "어드벤처 액션",
    "difficulty": 3,
    "activity": 5,
    "horror": 3,
    "description": "​ 마지막 모험후 자신이 재직중인 바네트 대학으로 돌아온 박사는 몇달간 비워두었던 개학 연구실에서 오래전에 도착한 소포를 발견하였다.\n소포중에는 아버지의 일기장 등이 있었다. 아버지의 흔적을 쫓는 도중 존슨박사는 우연히 만난 월터도노반에게서 아버지에 관련된 단서를 얻는다.\n도노반은 자신이 앙카라 북쪽에서 발견한 반쪽자리 신의 석판 탁폰을 보여주며 헨리박사의 일기장을 참고로 나머지 반쪽 석판과 예수가 최후의 만찬때 사용했다는 술장'성배'를 찾아달라고 부탁하는데...",
    "recommendation": "방이 많은 편! 활동성 최고의 테마를 찾으시는 분"
  },
  {
    "id": 21,
    "location": "대구광역시",
    "storeName": "마스터키 동성로점",
    "address": "대구광역시 중구 동성로5길 62",
    "phoneNumber": "0507-1317-7503",
    "homepage": "http://www.master-key.co.kr/booking/bk_detail?bid=9",
    "image": "http://www.master-key.co.kr/upload/room/60_img1.jpg",
    "title": "해리포터와 마법사의 돌",
    "genre": "판타지 퍼즐",
    "difficulty": 3,
    "activity": 4,
    "horror": 1,
    "description": "혜리는 호그와트 지하실에 `영원한 생을 가져다주는 마법사의 돌'이 비밀리에 보관되어 있다는 것을 알게되고, 해리의 부모님을 죽인 볼드모트가 그 돌을 노린다는 사실도 알게 된다.\n볼드모트는 바로 해리를 죽이려다 실패하고 이마에 번개모양의 흉터를 남긴 장본인이다. 해리는 볼드모트로부터 마법의 돌과 호그와트 마법학교를 지키기 위해 필사의 노력을 하는데... ​​",
    "recommendation": "해리포터 좀 봤다 하는 90년대 생"
  },
  {
    "id": 22,
    "location": "대구광역시",
    "storeName": "마스터키 동성로로데오점",
    "address": "대구광역시 중구 동성로5길 43",
    "phoneNumber": "0507-1316-7503",
    "homepage": "http://www.master-key.co.kr/booking/bk_detail?bid=14",
    "image": "http://www.master-key.co.kr/upload/room/87_img1.png",
    "title": "젊은 날",
    "genre": "감성",
    "difficulty": 3,
    "activity": 3,
    "horror": 2,
    "description": "“아픈 기억을 지워드립니다. Café. 젊은날 “\n아픈 기억을 지워준다는 글을 보고 찾아왔습니다. \n정말 이 차를 마시면 아픈 기억을 모두 지울 수 있나요?",
    "recommendation": "“아픈 기억을 지워드립니다.” 이 문구가 솔깃하신 분"
  },
  {
    "id": 23,
    "location": "대구광역시",
    "storeName": "마스터키 동성로로데오점",
    "address": "대구광역시 중구 동성로5길 43",
    "phoneNumber": "0507-1316-7503",
    "homepage": "http://www.master-key.co.kr/booking/bk_detail?bid=14",
    "image": "http://www.master-key.co.kr/upload/room/88_img1.png",
    "title": "필라멘트",
    "genre": "드라마 퍼즐",
    "difficulty": 3,
    "activity": 2,
    "horror": 1,
    "description": "10년의 세월을 날려버린 이 개떡 같은 꿈을 다 태워버리려 \n기름을 부을 수록 눈치없이 빛을 내던 그 열정의 순간들.\n\n작은 방안을 홀로 밝히는 저 끊어질 듯한 필라멘트를 바라보던 오늘.\n그리고 그 오늘은 또 같은 내일로.\n\n내 꿈은 어디로 가는가 또 무엇을 위해 버티고 있는가",
    "recommendation": "문제가 많은 방을 풀어야 돈이 아깝지 않으신 분"
  },
  {
    "id": 24,
    "location": "대구광역시",
    "storeName": "마스터키 동성로로데오점",
    "address": "대구광역시 중구 동성로5길 43",
    "phoneNumber": "0507-1316-7503",
    "homepage": "http://www.master-key.co.kr/booking/bk_detail?bid=14",
    "image": "http://www.master-key.co.kr/upload/room/89_img1.png",
    "title": "오버타임",
    "genre": "탈출 퍼즐",
    "difficulty": 5,
    "activity": 4,
    "horror": 1,
    "description": "글로벌 패션브랜드 MAKI\n동성로점 매니저 WEN의 좌충우돌 칼퇴 도전기\n\n열정페이는 너나하시고 난 페이열정.\n딱 입금 된 만큼의 열정! 오늘만큼은 꼭 칼퇴를 하겠다!",
    "recommendation": "너무 실감 나는 인테리어. 출근한 느낌이 들 정도라도 괜찮으신 분"
  },
  {
    "id": 25,
    "location": "대구광역시",
    "storeName": "마스터키 동성로로데오점",
    "address": "대구광역시 중구 동성로5길 43",
    "phoneNumber": "0507-1316-7503",
    "homepage": "http://www.master-key.co.kr/booking/bk_detail?bid=14",
    "image": "http://www.master-key.co.kr/upload/room/90_img1.png",
    "title": "가위",
    "genre": "스릴러 추리",
    "difficulty": 4,
    "activity": 3,
    "horror": 4,
    "description": "이상하리만치 월세가 싼 원룸.\n이 곳으로 이사오고 좋아하기도 잠시 \n나는 어제 오늘, 매일 가위에 눌린다.\n그리고 매일 반복되는 꿈속에서 나를 부르는 그녀 오늘은 꿈속에서 그녀를 따라가보기로 결심한다",
    "recommendation": "포스터만 공테. 예상치 못한 스토리를 경험해보고 싶으신 분"
  },
  {
    "id": 26,
    "location": "대구광역시",
    "storeName": "머더파커 대구점",
    "address": "대구광역시 중구 동성로3길 7",
    "phoneNumber": "053-254-4222",
    "homepage": "http://murderparker.com",
    "image": "http://murderparker.com/upload_file/room/1(15).jpg",
    "title": "PC방 가는길(Premium)",
    "genre": "코믹",
    "difficulty": 5,
    "activity": 5,
    "horror": 1,
    "description": "PC방 가는 길, 엘리베이터 앞에 떨어져 있는 수상한 암호가 적힌 카드를 발견했다. 이게 도대체 무엇일까? 뭔가 묘한 느낌에 엘리베이터 안을 둘러보는데….",
    "recommendation": "1세대나 1.5세대 유형에 익숙하신 분"
  },
  {
    "id": 27,
    "location": "대구광역시",
    "storeName": "머더파커 대구점",
    "address": "대구광역시 중구 동성로3길 7",
    "phoneNumber": "053-254-4222",
    "homepage": "http://murderparker.com",
    "image": "http://murderparker.com/upload_file/room/5(9).jpg",
    "title": "괴짜중딩 사차원",
    "genre": "미스터리",
    "difficulty": 4,
    "activity": 4,
    "horror": 1,
    "description": "우리 반에 아싸 있거든? 이름까지 ‘사차원’임ㅋㅋㅋㅋㅋㅋ 이거 진심 레알 실화ㅋㅋㅋㅋ 뭐 하는 건지 맨날 과학실이랑 쓰레기장 왔다 갔다 하는데 오늘도 이상한 쓰레기를 한 가득 들고 집에 가더라고? 그래서 내가 뒤따라가 봤지…",
    "recommendation": "기존의 문제 유형이나 진행 방식에 질리신 분"
  },
  {
    "id": 28,
    "location": "대구광역시",
    "storeName": "머더파커 대구점",
    "address": "대구광역시 중구 동성로3길 7",
    "phoneNumber": "053-254-4222",
    "homepage": "http://murderparker.com",
    "image": "http://murderparker.com/upload_file/room/3(10).jpg",
    "title": "백",
    "genre": "감성",
    "difficulty": 3,
    "activity": 3,
    "horror": 2,
    "description": "윽… 눈 부셔..",
    "recommendation": "관찰력으로 시작해서 관찰력으로 끝! 관찰력이 좋으신 분"
  },
  {
    "id": 29,
    "location": "대구광역시",
    "storeName": "머더파커 대구점",
    "address": "대구광역시 중구 동성로3길 7",
    "phoneNumber": "053-254-4222",
    "homepage": "http://murderparker.com",
    "image": "http://murderparker.com/upload_file/room/2.jpg",
    "title": "파커 VS 파커(Premium)",
    "genre": "스릴러",
    "difficulty": 4,
    "activity": 5,
    "horror": 4,
    "description": "어느 날 갑자기 사라진 딸 엘리스의 행방을 찾아 긴 시간을 헤매던 토니파커는 엘리스가 있다는 곳의 정보를 받아 찾아 나선다. 그 곳에서 만난 의외의 인물 김파커…. 그 둘의 운명은 과연…?",
    "recommendation": "흥미로운 전개 방식으로 몰입도가 높은 테마를 찾으시는 분"
  },
  {
    "id": 30,
    "location": "대구광역시",
    "storeName": "머더파커 대구점",
    "address": "대구광역시 중구 동성로3길 7",
    "phoneNumber": "053-254-4222",
    "homepage": "http://murderparker.com",
    "image": "http://murderparker.com/upload_file/room/4(12).jpg",
    "title": "8585세탁소",
    "genre": "드라마 슬픔 병맛",
    "difficulty": 2,
    "activity": 4,
    "horror": 1,
    "description": "이 동네에서 제일 잘나가는 완벽한 특수 빨래, 수선 전문점 8585 세탁소 주인 표벽재. 가끔 수상한 빨래들이 와서 이상한 느낌이 들기도 했지만, 어차피 나는 열심히 빨아서 돈이나 벌면 그만이었다. 그러던 어느 날, 내 금쪽같은 아들이 갑자기 사라졌다. 이젠 모든 것이 의심스럽다. 내 아들을 찾기 위해서라면 어떤 일도 할 수 있어…",
    "recommendation": "문제에 접근하는 센스가 어느 정도 있으신 분"
  },
  {
    "id": 31,
    "location": "대구광역시",
    "storeName": "머더파커 대구2호점",
    "address": "대구광역시 중구 동성로3길 8",
    "phoneNumber": "0507-1389-4223",
    "homepage": "http://murderparker.com",
    "image": "http://murderparker.com/upload_file/room/타깃.jpg",
    "title": "타겟",
    "genre": "스릴러",
    "difficulty": 5,
    "activity": 3,
    "horror": 4,
    "description": "너희는 언제나 내 타겟이었지. 오늘도 역시...",
    "recommendation": "상당히 까다로운 난이도의 문제도 OK이신 분"
  },
  {
    "id": 32,
    "location": "대구광역시",
    "storeName": "머더파커 대구2호점",
    "address": "대구광역시 중구 동성로3길 8",
    "phoneNumber": "0507-1389-4223",
    "homepage": "http://murderparker.com",
    "image": "http://murderparker.com/upload_file/room/사건의재구성.jpg",
    "title": "사건의 재구성(Premium)",
    "genre": "미스터리",
    "difficulty": 4,
    "activity": 5,
    "horror": 3,
    "description": "5년 전 일어난 사고로 아들은 지금까지 혼수상태에 빠져있다. 착하던 내 아들이 일진 친구들과 어울려 오토바이를 탔다니... 내 아들이 일진이라고? 도대체 무슨 일이 있었던 걸까. 알아내야겠다. 요즘 뇌세포만 있으면 혼수상태인 사람의 이전 기억을 보여주는 업체가 생겼다던데... 한번 의뢰해볼까...?",
    "recommendation": "활동성이 높지 않아 땀 흘리는 게 싫으신 분"
  },
  {
    "id": 33,
    "location": "대구광역시",
    "storeName": "머더파커 대구2호점",
    "address": "대구광역시 중구 동성로3길 8",
    "phoneNumber": "0507-1389-4223",
    "homepage": "http://murderparker.com",
    "image": "http://murderparker.com/upload_file/room/전국일이삼.jpg",
    "title": "전국일이삼",
    "genre": "잠입",
    "difficulty": 4,
    "activity": 4,
    "horror": 3,
    "description": "이 곳은 전국 고3들 중 수재of수재들만 모인다는 프리미엄 독서실. 난 77등... 운 좋게 이 독서실에 들어올 수 있었다. 우연히 들었는데 내가 있는 층에는 전국 1,2,3등이 다 있다고 한다. 10등 안에 들 수만 있다면 무엇이든지 할텐데... 안되겠다, 오늘 저 녀석들 방에 몰래 들어가서 학습노트를 훔쳐야겠다.",
    "recommendation": "나름대로의 매력이 있는 이야기를 즐기시는 분"
  },
  {
    "id": 34,
    "location": "대구광역시",
    "storeName": "머더파커 대구2호점",
    "address": "대구광역시 중구 동성로3길 8",
    "phoneNumber": "0507-1389-4223",
    "homepage": "http://murderparker.com",
    "image": "http://murderparker.com/upload_file/room/도레미용실(2).jpg",
    "title": "도레미용실",
    "genre": "감성",
    "difficulty": 2,
    "activity": 3,
    "horror": 2,
    "description": "우리 동네 사랑방이자 뷰티의 메카 ‘도레미용실’ 원장이던 언니가 병으로 갑작스럽게 세상을 떠난 후, 내가 이 미용실을 이어받았다. 언니가 없는 동안 손님이 많이 떨어졌겠지만...열심히 해봐야지..!",
    "recommendation": "쉽고 재치있는 문제들로 텐션을 꽤나 올려서 플레이 하시고 싶은 분"
  },
  {
    "id": 35,
    "location": "대구광역시",
    "storeName": "비밀의화원 동성로점",
    "address": "대구광역시 중구 동성로5길 55",
    "phoneNumber": "070-8823-0070",
    "homepage": "http://www.secretgardenescape.com",
    "image": "http://www.secretgardenescape.com/pimages/Product/Pr_1584492859.jpg",
    "title": "안녕",
    "genre": "공포",
    "difficulty": 2,
    "activity": 3,
    "horror": 5,
    "description": "과로로 쓰러진 당신, 입원 도중 정신을 잃고 낯선 곳에 갇혔다. 여기가 어디지!?",
    "recommendation": "무서울수록 스릴을 느끼는 분"
  },
  {
    "id": 36,
    "location": "대구광역시",
    "storeName": "비밀의화원 동성로점",
    "address": "대구광역시 중구 동성로5길 55",
    "phoneNumber": "070-8823-0070",
    "homepage": "http://www.secretgardenescape.com",
    "image": "http://www.secretgardenescape.com/pimages/Product/Pr_1565770435.jpg",
    "title": "비밀의 선물",
    "genre": "감성로맨스",
    "difficulty": 3,
    "activity": 2,
    "horror": 2,
    "description": "아내가 집으로 돌아오기 한시간 전. 그녀를 위한 선물을 준비하자!",
    "recommendation": "깔끔하고 인테리어가 예쁜 테마를 좋아하시는 분"
  },
  {
    "id": 37,
    "location": "대구광역시",
    "storeName": "비밀의화원 동성로점",
    "address": "대구광역시 중구 동성로5길 55",
    "phoneNumber": "070-8823-0070",
    "homepage": "http://www.secretgardenescape.com",
    "image": "http://www.secretgardenescape.com/pimages/Product/Pr_1565770414.jpg",
    "title": "대감댁 변씨",
    "genre": "조선므훗병맛",
    "difficulty": 5,
    "activity": 4,
    "horror": 1,
    "description": "마님과 좋은 시간을 보내고 잠이 든 변씨! 아뿔싸 벌써 대감님이 돌아오기 한 시간전! 과연 변씨는 대감님이 돌아오시기전에 모든 일을 끝낼 수 있을 것인가!",
    "recommendation": "19금은 아니고 15금 정도를 찾으시는 분"
  },
  {
    "id": 38,
    "location": "대구광역시",
    "storeName": "비밀의화원 동성로점",
    "address": "대구광역시 중구 동성로5길 55",
    "phoneNumber": "070-8823-0070",
    "homepage": "http://www.secretgardenescape.com",
    "image": "http://www.secretgardenescape.com/pimages/Product/Pr_1584492761.jpg",
    "title": "리비도",
    "genre": "성인",
    "difficulty": 4,
    "activity": 3,
    "horror": 3,
    "description": "옆 대저택에 살고 있는 아름다운 미망인, 그녀의 실루엣. 나도 모르게 그녀의 집에 들어갔다가 발견한 짙은 빨간색 초대장. 그녀와의 낯설지만 야릇한 헤프닝속에 느껴지는 익숙한 향기. 당신은 과연, 그녀의 초대장에 숨겨진 퍼즐을 맞출 수 있을 것인가!?",
    "recommendation": "책이나 영화를 보는 관객이 된 듯한 자세로 므흣하고 싶으신 분"
  },
  {
    "id": 39,
    "location": "대구광역시",
    "storeName": "비밀의화원 동성로점",
    "address": "대구광역시 중구 동성로5길 55",
    "phoneNumber": "070-8823-0070",
    "homepage": "http://www.secretgardenescape.com",
    "image": "http://www.secretgardenescape.com/pimages/Product/Pr_1584492808.jpg",
    "title": "대×9탈출",
    "genre": "코믹",
    "difficulty": 3,
    "activity": 3,
    "horror": 1,
    "description": "오늘도 평화로운 대구광역시 동물원의 밤.",
    "recommendation": "대구광역시에서만 맛볼 수 있는 고퀄리티 방을 찾으시는 분"
  },
  {
    "id": 40,
    "location": "대구광역시",
    "storeName": "비밀의화원 동성로점",
    "address": "대구광역시 중구 동성로5길 55",
    "phoneNumber": "070-8823-0070",
    "homepage": "http://www.secretgardenescape.com",
    "image": "http://www.secretgardenescape.com/pimages/Product/Pr_1579160943.jpg",
    "title": "영웅을 찾아서",
    "genre": "미션",
    "difficulty": 2,
    "activity": 3,
    "horror": 2,
    "description": "대한민국 의열단으로 독립투사들을 수호하는 정예집단의 일원인 당신. 대한민국의 독립을 앞둔 어느 날, 당신은 서대문 형무소 지하 감옥에 우리의 영웅들이 이감되어 있다는 소식을 듣게 된다. 과연 영웅들을 구하고 대한민국의 독립을 이뤄나갈 수 있을 것인가?",
    "recommendation": "직관적이고 관찰력이 중요한 테마를 좋아하시는 분"
  },
  {
    "id": 41,
    "location": "대구광역시",
    "storeName": "비밀의화원 동성로점",
    "address": "대구광역시 중구 동성로5길 55",
    "phoneNumber": "070-8823-0070",
    "homepage": "http://www.secretgardenescape.com",
    "image": "http://www.secretgardenescape.com/pimages/Product/Pr_1565770368.jpg",
    "title": "향수 2019",
    "genre": "공포스릴러",
    "difficulty": 4,
    "activity": 4,
    "horror": 4,
    "description": "세계적으로 유명한 향수 가게를 방문한 당신은 향수를 구경하던 중 갑자기 정신을 잃고 만다. 정신을 차려보니 손발은 묶여 있는 채로 방 안에 갇혀 있다는 것을 알게 된다.어두컴컴한 조명과 불쾌한 약품 냄새... 아무래도 당장 이 곳을 나가야만 할 것 같다..!",
    "recommendation": "공포 테마지만 삑딱쿵이 심하지 않은 테마를 선호하시는 분"
  },
  {
    "id": 42,
    "location": "대구광역시",
    "storeName": "비트포비아 동성로점",
    "address": "대구광역시 중구 동성로6길 33",
    "phoneNumber": "0507-1403-4760",
    "homepage": "https://www.xphobia.net",
    "image": "https://www.xphobia.net/data/item/1476102475/7IY7Jqw_3illust_170.jpg",
    "title": "쏘우",
    "genre": "호러",
    "difficulty": 7,
    "activity": 3,
    "horror": 5,
    "description": "“자, 게임을 시작하지”\n\n지금까지 평범한 일상을 보내던 사람들이 \n영문도 모른 채 발목엔 쇠줄이 묶여,\n낯선 공간에서 하나 둘 씩 눈을 뜨기 시작한다..\n\n우왕좌왕 공포감에 질려가는 그들 앞에, 한 비디오 영상이 플레이되는데…\n“치이이익….. 치익… 모두 일어났는가..? 그럼 게임을 시작하지”\n정체 모를 괴한의 막무가내 제안.\n\n살고 싶다면 목숨을 건 이 GAME에 응해야만 한다.\n당신은 살아서 나갈 것인가, 아니면 이대로 삶을 포기할 것인가.",
    "recommendation": "공포 테마 입문자"
  },
  {
    "id": 43,
    "location": "대구광역시",
    "storeName": "비트포비아 동성로점",
    "address": "대구광역시 중구 동성로6길 33",
    "phoneNumber": "0507-1403-4760",
    "homepage": "https://www.xphobia.net",
    "image": "https://www.xphobia.net/data/item/조커_illust_170.png",
    "title": "웃는 남자",
    "genre": "호러",
    "difficulty": 5,
    "activity": 3,
    "horror": 5,
    "description": "“걸리지 않게 조심해, 들키는 순간 네 입도 찢어지고 말거야.”\n\n신입 수습기자로 일하고 있는 당신,\n기사거리를 찾던 중, 입이 찢어진 아이들이 세계 각지로 팔려가고 있다는 사실을 알게 된다.\n“이거 예상치 못한 특종인걸…?”\n사건을 낱낱히 파헤치기 위해 서커스장으로의 잠입은 성공했지만,\n아이들이 보이지 않는다.\n\n과연 당신은 1시간 안에 특종에 대한 단서와, 아이들을 구할 수 있을까?\n\n'한 순간도 긴장을 놓지마.\n만약 그에게 걸린다면 당신의 입도 찢어지고 말거야…..’",
    "recommendation": "공포라기 보단 호러 느낌. 호러틱한 스토리를 좋아하시는 분"
  },
  {
    "id": 44,
    "location": "대구광역시",
    "storeName": "비트포비아 동성로점",
    "address": "대구광역시 중구 동성로6길 33",
    "phoneNumber": "0507-1403-4760",
    "homepage": "https://www.xphobia.net",
    "image": "https://www.xphobia.net/data/item/1476092038/7YWM65s_3illust_170.png",
    "title": "테러 라이브",
    "genre": "스릴러",
    "difficulty": 4,
    "activity": 4,
    "horror": 4,
    "description": "“알 수 없는 테러, 회사가 무너졌다.”\n\n평범한 회사원인 당신.\n평소와 같이 출근하여 일하고 있던 중\n갑자기 무너져 내린 회사 안에 갇히고 만다.\n눈에 보이는 것은 무너져 내리는 사무실 속 콘크리트 잔해들 밖에 없는데…..\n유일한 탈출 방법은 이곳에 있는 비상대피요령을 찾는 방법 뿐.\n\n‘우리 여기서 살아서 나갈 수 있을까……?’\n\n더 이상 건물이 무너지기 전 찾아내어 탈출해야 한다.\n생존을 위한 탈출이 시작된다.",
    "recommendation": "어렵게 실마리를 찾아나가는 과정을 즐기시는 분"
  },
  {
    "id": 45,
    "location": "대구광역시",
    "storeName": "비트포비아 동성로점",
    "address": "대구광역시 중구 동성로6길 33",
    "phoneNumber": "0507-1403-4760",
    "homepage": "https://www.xphobia.net",
    "image": "https://www.xphobia.net/data/item/1476077160/1476085523_0121_7ZmN64yA_7Yq466CI7J2065Oc.png",
    "title": "트레이드",
    "genre": "스릴러",
    "difficulty": 4,
    "activity": 4,
    "horror": 4,
    "description": "“탈출하지 못하면, 나는 그들에게 넘겨진다.”\n\n해외 출장중,\n지친 하루를 달래러 잠시 들린 bar에서 한 여자가 내게 다가온다.\n“피곤해 보이네, 같이 한잔 할래?”\n\n그녀가 건넨 칵테일을 마시자 바로 의식이 희미해진다.\n눈을 떠 보니, 외딴 지하실. 온몸은 쇠사슬에 묶여 움직일 수 없다.\n\n그 때 밖에서 들려오는 목소리.\n“물건은 확보되었다. 한 시간 후에 넘기도록 하지”\n\n1시간 안에 나가야만 내가 살 수 있다.",
    "recommendation": "난이도가 살짝 있는 게 오히려 좋으신 분"
  },
  {
    "id": 46,
    "location": "대구광역시",
    "storeName": "비트포비아 동성로점",
    "address": "대구광역시 중구 동성로6길 33",
    "phoneNumber": "0507-1403-4760",
    "homepage": "https://www.xphobia.net",
    "image": "https://www.xphobia.net/data/item/용의선상.png",
    "title": "용의선상",
    "genre": "드라마",
    "difficulty": 5,
    "activity": 2,
    "horror": 3,
    "description": "피시방에서 라면을 하나 훔쳐먹다\n재수없게(?) 경찰에게 걸렸다\n아 그래 인정한다고! 근데 뭐?\n내가 연쇄살인용의자라고? 미치겠네!\n내일이면 유치장이 아닌 진짜 깜빵에 가는날 ..\n\n내 무죄는 내가 증명한다..!!",
    "recommendation": "스토리랑 장치의 연관성이 높아요! 몰입감이 중요하신 분"
  },
  {
    "id": 47,
    "location": "대구광역시",
    "storeName": "비트포비아 동성로점",
    "address": "대구광역시 중구 동성로6길 33",
    "phoneNumber": "0507-1403-4760",
    "homepage": "https://www.xphobia.net",
    "image": "https://www.xphobia.net/data/item/모자가게의%20비밀_Illust.png",
    "title": "모자가게의 비밀",
    "genre": "판타지",
    "difficulty": 1,
    "activity": 4,
    "horror": 2,
    "description": "“저주를 풀지 못하면, 영원히 노파의 모습으로 살아가야 해..”\n\n모자가게에서 일하며 무료한 하루하루를 보내던 당신에게,\n황야의 마녀가 찾아왔다.\n\n“주어진 소중함을 모르는 너희에게 젊음은 사치야!”\n\n영문도 모른 채 마녀의 저주로 인해 할머니가 된 당신.\n거울을 보니 당신은 늙은 노파가 되어있고,\n60분 안에 마법을 풀지 못하면 평생 그 모습으로 살아가야 하는데..",
    "recommendation": "아름다운 인테리어 디자인 테마를 하고 싶은 초심자, 입문자"
  },
  {
    "id": 48,
    "location": "대구광역시",
    "storeName": "비트포비아 동성로점",
    "address": "대구광역시 중구 동성로6길 33",
    "phoneNumber": "0507-1403-4760",
    "homepage": "https://www.xphobia.net",
    "image": "https://www.xphobia.net/data/item/대학로_illustration_잭더리퍼.png",
    "title": "잭 더 리퍼",
    "genre": "호러",
    "difficulty": 3,
    "activity": 4,
    "horror": 5,
    "description": "“악명높은 살인마 잭 더 리퍼에게 걸린 이번 희생자가 누구야?\n\n이곳은 영국 런던거리, 그러나 사람 그림자도 보이지 않는다.\n왜냐고? 흉악한 연쇄 살인마 잭 더 리퍼가 돌아다니기 때문이지.\n\n“이번 살인은 60분 뒤, 이 곳에서 하겠다!”\n\n참혹한 살인현장에 다음 예고 살인에 대한 흔적을 남긴 잭 더 리퍼,\n남은 시간은 60분,\n희생자가 누군지 밝혀 내 그의 악마 같은 행위를 막아야한다.\n\n그의 살인 행위를 막을 수 있는 유일한 희망은 당신 뿐.",
    "recommendation": "너무 많은 생각 이전에 바로 행동으로 옮기시는 분"
  },
  {
    "id": 49,
    "location": "대구광역시",
    "storeName": "비트포비아 동성로점",
    "address": "대구광역시 중구 동성로6길 33",
    "phoneNumber": "0507-1403-4760",
    "homepage": "https://www.xphobia.net",
    "image": "https://www.xphobia.net/data/item/심야식당_Illust.png",
    "title": "심야식당",
    "genre": "드라마",
    "difficulty": 2,
    "activity": 3,
    "horror": 3,
    "description": "“비밀 소스를 찾는 자, 심야식당의 후계자가 되리라”\n\n도쿄의 번화가, 언제나 사람들로 가득한 밥집이 있다.\n바로 내가 일하는 곳, ‘심야식당’\n\n어느 날 갑자기 찾아온 마스터의 사망소식, 그와 함께 발견 된 유언장.\n“이 가게의 비밀 소스와, 경영 노하우를 찾는 제자에게 이 가게를 물려주겠다.!”\n그 속에 써있는 문구가 나의 승부욕을 자극시켰다.\n\n심야식당의 경영권을 갖기 위해 비밀을 파헤치기로 결심한 나..\n나는 심야식당의 비밀 레시피를 얻을 수 있을까?",
    "recommendation": "자연스러운 스토리 연결을 좋아하시는 분"
  },
  {
    "id": 50,
    "location": "대구광역시",
    "storeName": "셜록홈즈 동성로점",
    "address": "대구광역시 중구 동성로5길 45",
    "phoneNumber": "053-253-2225",
    "homepage": "http://sherlock-holmes.co.kr",
    "image": "https://blog.kakaocdn.net/dn/bDcdkD/btrirwg3lY7/UxdveKvO2pRKstgy8B7XwK/img.jpg",
    "title": "지프리트의 심장",
    "genre": "판타지",
    "difficulty": 4,
    "activity": 4,
    "horror": 3,
    "description": "[플리퍼 시티 에피소드 01] 잊혀진 이야기 속에 전해지는 순수 에너지의 결정체 \"지프리트의 심장\"을 찾기 위해 플리퍼 시티를 헤매던 일행. 마을 외곽의 한 골동품 점에서 가고자 하는 곳의 좌표를 알려준다는 검은 주사위를 얻는다. 검은 주사위가 만들어 준 좌표를 통해 도착한 곳은 알 수 없는 낡은 기관실. 그곳의 수수께끼를 풀고 지프리트의 심장을 찾아낼 수 있을까",
    "recommendation": "1세대의 매운 맛을 느껴보고 싶으신 분"
  },
  {
    "id": 51,
    "location": "대구광역시",
    "storeName": "셜록홈즈 동성로점",
    "address": "대구광역시 중구 동성로5길 45",
    "phoneNumber": "053-253-2225",
    "homepage": "http://sherlock-holmes.co.kr",
    "image": "https://blog.kakaocdn.net/dn/bpK8Za/btrpxyd0cv4/0ZTgDQ8Io8PZdTb3WNi6uk/img.png",
    "title": "황금감옥: 와캄",
    "genre": "판타지",
    "difficulty": 3,
    "activity": 4,
    "horror": 3,
    "description": "지금까지 봐왔던 감옥들과는 사뭇 다른 분위기의 낯선 감옥. 그 안에서 펼쳐진 끝을 알 수 없는 새로운 이야기. 이전까지 경험할 수 없었던 색다른 테마가 당신을 기다립니다.",
    "recommendation": "탈출하지 못할까봐 의기소침해서 도전을 못하는 분들"
  },
  {
    "id": 52,
    "location": "대구광역시",
    "storeName": "셜록홈즈 동성로점",
    "address": "대구광역시 중구 동성로5길 45",
    "phoneNumber": "053-253-2225",
    "homepage": "http://sherlock-holmes.co.kr",
    "image": "https://img1.daumcdn.net/thumb/R800x0/?scode=mtistory2&fname=https%3A%2F%2Fblog.kakaocdn.net%2Fdn%2FNEucP%2FbtrkcrkPNBq%2F19lO2BbS3tMDqYWoV5jgTk%2Fimg.jpg",
    "title": "랑슈 뷰티연구소",
    "genre": "드라마",
    "difficulty": 3,
    "activity": 3,
    "horror": 2,
    "description": "당신의 아름다움을 찾아드립니다.",
    "recommendation": "방 안을 잘 살필 수 있는 관찰력을 갖추신 분"
  },
  {
    "id": 53,
    "location": "대구광역시",
    "storeName": "셜록홈즈 동성로점",
    "address": "대구광역시 중구 동성로5길 45",
    "phoneNumber": "053-253-2225",
    "homepage": "http://sherlock-holmes.co.kr",
    "image": "https://blog.kakaocdn.net/dn/crMYsy/btrp1HhK025/R4jYUK63kOTLfC0LxdDtD0/img.png",
    "title": "단잠",
    "genre": "감성",
    "difficulty": 3,
    "activity": 3,
    "horror": 2,
    "description": "몸도 마음도 지친 퇴근길, 지하철역에서 마주한 낯선 포스터 하나. 지친 당신에게 위로가 될 피아노 콘서트 : 단잠. 지금 시작합니다.",
    "recommendation": "복잡한 문제도 척하면 척 의도를 읽어내시는 분"
  },
  {
    "id": 54,
    "location": "대구광역시",
    "storeName": "앨리스 이스케이프",
    "address": "대구광역시 중구 동성로6길 2-5",
    "phoneNumber": "0507-1410-8788",
    "homepage": "http://www.alice-escape.com",
    "image": "http://www.alice-escape.com/upload_file/room/room2_1.jpg",
    "title": "금두꺼비",
    "genre": "드라마",
    "difficulty": 2,
    "activity": 3,
    "horror": 1,
    "description": "",
    "recommendation": "등잔 밑이 어둡다! 섬세하고 침착하신 분"
  },
  {
    "id": 55,
    "location": "대구광역시",
    "storeName": "앨리스 이스케이프",
    "address": "대구광역시 중구 동성로6길 2-5",
    "phoneNumber": "0507-1410-8788",
    "homepage": "http://www.alice-escape.com",
    "image": "http://www.alice-escape.com/upload_file/room/room5_1.jpg",
    "title": "레드 주식회사",
    "genre": "호러",
    "difficulty": 5,
    "activity": 3,
    "horror": 3,
    "description": "",
    "recommendation": "실제 영화를 기반으로한 디테일을 원하시는 분"
  },
  {
    "id": 56,
    "location": "대구광역시",
    "storeName": "앨리스 이스케이프",
    "address": "대구광역시 중구 동성로6길 2-5",
    "phoneNumber": "0507-1410-8788",
    "homepage": "http://www.alice-escape.com",
    "image": "http://www.alice-escape.com/upload_file/room/room8_1.jpg",
    "title": "지퍼스 크리퍼스",
    "genre": "호러",
    "difficulty": 5,
    "activity": 2,
    "horror": 5,
    "description": "",
    "recommendation": "신박한 장치가 그저 좋은 방생아"
  },
  {
    "id": 57,
    "location": "대구광역시",
    "storeName": "앨리스 이스케이프",
    "address": "대구광역시 중구 동성로6길 2-5",
    "phoneNumber": "0507-1410-8788",
    "homepage": "http://www.alice-escape.com",
    "image": "http://www.alice-escape.com/upload_file/room/room4_1.jpg",
    "title": "왕따 교실",
    "genre": "드라마 & 호러",
    "difficulty": 2,
    "activity": 2,
    "horror": 3,
    "description": "",
    "recommendation": "으스스한 분위기에 압도되지 않을 강심장"
  },
  {
    "id": 58,
    "location": "대구광역시",
    "storeName": "앨리스 이스케이프",
    "address": "대구광역시 중구 동성로6길 2-5",
    "phoneNumber": "0507-1410-8788",
    "homepage": "http://www.alice-escape.com",
    "image": "http://www.alice-escape.com/upload_file/room/room7_1.jpg",
    "title": "사가와 잇세이",
    "genre": "호러",
    "difficulty": 5,
    "activity": 4,
    "horror": 4,
    "description": "",
    "recommendation": "무서운 건 좋아하지만 어두운 건 싫어하시는 분"
  },
  {
    "id": 59,
    "location": "대구광역시",
    "storeName": "앨리스 이스케이프",
    "address": "대구광역시 중구 동성로6길 2-5",
    "phoneNumber": "0507-1410-8788",
    "homepage": "http://www.alice-escape.com",
    "image": "http://www.alice-escape.com/upload_file/room/room9_1.jpg",
    "title": "동성로 앨리스",
    "genre": "판타지",
    "difficulty": 3,
    "activity": 5,
    "horror": 1,
    "description": "",
    "recommendation": "대표 테마부터 정복해보고 싶으신 분"
  },
  {
    "id": 60,
    "location": "대구광역시",
    "storeName": "앨리스 이스케이프",
    "address": "대구광역시 중구 동성로6길 2-5",
    "phoneNumber": "0507-1410-8788",
    "homepage": "http://www.alice-escape.com",
    "image": "http://www.alice-escape.com/upload_file/room/room3_1.jpg",
    "title": "달빛 서커스",
    "genre": "판타지",
    "difficulty": 2,
    "activity": 3,
    "horror": 2,
    "description": "",
    "recommendation": "능동형 액션을 선호하시는 분"
  },
  {
    "id": 61,
    "location": "대구광역시",
    "storeName": "앨리스 이스케이프",
    "address": "대구광역시 중구 동성로6길 2-5",
    "phoneNumber": "0507-1410-8788",
    "homepage": "http://www.alice-escape.com",
    "image": "http://www.alice-escape.com/upload_file/room/room1_1.jpg",
    "title": "아빠의 서재",
    "genre": "드라마/19금",
    "difficulty": 3,
    "activity": 3,
    "horror": 1,
    "description": "",
    "recommendation": "비주얼 어택으로 잠깐 뇌가 정지되고 싶으신 분"
  },
  {
    "id": 62,
    "location": "대구광역시",
    "storeName": "앨리스 이스케이프",
    "address": "대구광역시 중구 동성로6길 2-5",
    "phoneNumber": "0507-1410-8788",
    "homepage": "http://www.alice-escape.com",
    "image": "http://www.alice-escape.com/upload_file/room/크루즈%20최종(1).jpg",
    "title": "환상 크루즈",
    "genre": "판타지",
    "difficulty": 5,
    "activity": 4,
    "horror": 1,
    "description": "",
    "recommendation": "항로를 찾아 크루즈를 탈출! 거대한 스케일을 느껴보고 싶으신 분"
  },
  {
    "id": 63,
    "location": "대구광역시",
    "storeName": "이스케이퍼스 대구동성로점",
    "address": "대구광역시 중구 동성로6길 22",
    "phoneNumber": "053-710-5222",
    "homepage": "https://escapersd.com/theme/9",
    "image": "https://escapersd.com/storage/1wf88SSPK2N4oKIGDLdqro9RpQ8gQ5HfhqXHxNQ0.jpg",
    "title": "멍스타그램",
    "genre": "감성",
    "difficulty": 3,
    "activity": 3,
    "horror": 1,
    "description": "당신은 개를 좋아하시나요?\"\n당신은 모르는 개들의 은밀한 SNS.\n고양이를 더 좋아하셔도 보여는 드릴게요!",
    "recommendation": "눈물이 핑 도는 스토리를 찾으시는 분"
  },
  {
    "id": 64,
    "location": "대구광역시",
    "storeName": "이스케이퍼스 대구동성로점",
    "address": "대구광역시 중구 동성로6길 22",
    "phoneNumber": "053-710-5222",
    "homepage": "https://escapersd.com/theme/9",
    "image": "https://escapersd.com/storage/2p7Xk7TMQ1qGxGzz2gYthFf5e17rhNS0E632b2vl.jpg",
    "title": "폰부스",
    "genre": "공포",
    "difficulty": 3,
    "activity": 3,
    "horror": 5,
    "description": "내 여자친구 수현이...\n그 날 도대체 수현이에게 무슨 일이 있었던걸까.\n수현이 근처에서 어슬렁 거리던 그 놈 짓이 분명하다.",
    "recommendation": "신선한 소재의 테마를 찾으시는 분"
  },
  {
    "id": 65,
    "location": "대구광역시",
    "storeName": "이스케이퍼스 대구동성로점",
    "address": "대구광역시 중구 동성로6길 22",
    "phoneNumber": "053-710-5222",
    "homepage": "https://escapersd.com/theme/9",
    "image": "https://escapersd.com/storage/3wwWbiXwiI7mJ5oOPpNZUrJEIdoq3G7v3VbLNiH2.jpg",
    "title": "웰컴 투 캔디샵",
    "genre": "감성",
    "difficulty": 4,
    "activity": 3,
    "horror": 2,
    "description": "잠을 못 잔지가 벌써 1년이다.\n저번에 그놈이 준 마법캔디만 있으면 되는데\n오늘이 영업 마지막 날이라니.\n내가 훔쳐서라도 만들고만다.\n숙면캔디!!!",
    "recommendation": "확실히 컨텐츠로 승부하는 방탈출을 원하시는 분"
  },
  {
    "id": 66,
    "location": "대구광역시",
    "storeName": "이스케이퍼스 대구동성로점",
    "address": "대구광역시 중구 동성로6길 22",
    "phoneNumber": "053-710-5222",
    "homepage": "https://escapersd.com/theme/9",
    "image": "https://escapersd.com/storage/IRKiCKvQWbS2bCzZHxP0h4o1jzEYeAZaRqHf0qxn.jpg",
    "title": "돈싱크",
    "genre": "바이러스",
    "difficulty": 5,
    "activity": 3,
    "horror": 2,
    "description": "전 세계에 바이러스가 퍼졌다.\n공기중으로 전파되는 바이러스는 감염시\n아무것도 생각하기 싫은 강력한 무기력을 느끼게 된다.\n난 오늘부터 이 지하벙커에 생활하게 되었다.",
    "recommendation": "문제 푸는 테마를 좋아하시는 분"
  },
  {
    "id": 67,
    "location": "대구광역시",
    "storeName": "이스케이퍼스 대구동성로점",
    "address": "대구광역시 중구 동성로6길 22",
    "phoneNumber": "053-710-5222",
    "homepage": "https://escapersd.com/theme/9",
    "image": "https://escapersd.com/storage/0MTdK2ifMpQuDzpjuMPha5I3LQauoTd8FuQuQgJ1.jpg",
    "title": "서커스: 동성극단의 사정",
    "genre": "미스터리",
    "difficulty": 4,
    "activity": 4,
    "horror": 4,
    "description": "동성로에 서커스장이 오픈했다는 소문을 들었다.\n오픈 기념으로 무료 공연을 한다고 하여 친구들과 보러 가기로 했다.\n설레서 잠이 오지 않는다.\n\n그런데 뭔가 이상하다..\n분명 동성극단은 몇 년 전 사라졌는데?\n\n- 이 테마는 약간의 공포 요소를 포함하고 있습니다.\n- 치마를 입으셨을 때 이용에 불편을 겪으실 수 있습니다.",
    "recommendation": "친절한 가이드에 따라 자연스럽게 이어지는 테마를 찾으시는 분"
  },
  {
    "id": 68,
    "location": "대구광역시",
    "storeName": "이스케이퍼스 대구동성로점",
    "address": "대구광역시 중구 동성로6길 22",
    "phoneNumber": "053-710-5222",
    "homepage": "https://escapersd.com/theme/9",
    "image": "https://escapersd.com/storage/iUKQ4dMUnzXq5V6Uhl6kThajx60ZLJp3BZ9EA7LX.jpg",
    "title": "끝까지 간다",
    "genre": "첩보",
    "difficulty": 5,
    "activity": 5,
    "horror": 3,
    "description": "나는 38기동대의 엘리트 세금 징수원이 되는 것이 목표이다.\n얼마 전 친한 후배가 고액체납자 K의 집에서 빈손으로 돌아왔다고 하며 도움을 청했다.\n이번 업무만 잘 마무리하면 나도 엘리트 세금 징수원이 될 수 있다.\n\n이번에야말로 나의 능력을 보여주겠어.\n반드시..!",
    "recommendation": "달성도 100%를 채울 때의 아드레날린을 느끼고 싶으신 분"
  },
  {
    "id": 69,
    "location": "대구광역시",
    "storeName": "지구별방탈출",
    "address": "대구광역시 중구 동성로 15-1",
    "phoneNumber": "053-214-6277",
    "homepage": "https://지구별.com",
    "image": "https://지구별.com/storage/MGQKas5zFxLbmBcveObYl4CfoXobfLiF9U6R5qC0.jpg",
    "title": "단디해라",
    "genre": "코믹",
    "difficulty": 3,
    "activity": 5,
    "horror": 1,
    "description": "멸종 위기의 지구별. 드디어 우리는 인간이 살 수 있는 외계행성을 발견했다.\n새로운 세계에 대한 갈망으로 폭주한 지원경쟁을 뚫고, 혹독한 행성 환경을 탐사하기 위한 최종 선발대 트레이닝 과정에 입소한 당신.\n당신은 인류의 위대한 영웅이 될 자격이 있는가?",
    "recommendation": "“스케일 멋즤당” 소리가 절로 나오는 방을 찾으시는 분"
  },
  {
    "id": 70,
    "location": "대구광역시",
    "storeName": "지구별방탈출",
    "address": "대구광역시 중구 동성로 15-1",
    "phoneNumber": "053-214-6277",
    "homepage": "https://지구별.com",
    "image": "https://지구별.com/storage/KgsFqaYEgTteKGceTRlJLxJVBx6Jn2fB0xJGD8aU.jpg",
    "title": "만월 (꿈을 훔치는 요괴)",
    "genre": "잠입,미스터리",
    "difficulty": 4,
    "activity": 4,
    "horror": 1,
    "description": "베트남 꽝남성 호이안 외곽의 작은 마을 빈디엔.\n이 작은 마을엔 보름달이 뜨는 밤, 꿈을 훔치는 요괴가 나타난다는 전설이 있다.\n\n꿈도둑으로 취업한 신입 요괴 '뉴엉'의 첫 업무는 빈디엔에서 꿈을 훔쳐오는 것.\n\n자, 업무 시작이다!",
    "recommendation": "주변 관찰력이 매우매우매우 좋으신 분"
  },
  {
    "id": 71,
    "location": "대구광역시",
    "storeName": "지구별방탈출",
    "address": "대구광역시 중구 동성로 15-1",
    "phoneNumber": "053-214-6277",
    "homepage": "https://지구별.com",
    "image": "https://지구별.com/storage/mNFG47fdDOMJAd94iA7hXOy5bMzIN4W6kRNfMjRq.jpg",
    "title": "너의 겨울은 가고 봄은 온다",
    "genre": "감성",
    "difficulty": 2,
    "activity": 4,
    "horror": 1,
    "description": "내 이름은 인카. 핀란드 산타마을 로바니에미의 산타클로스다.\n올해 선물 배달의 주인공을 배정받았는데, 바로 마을 최악의\n장난꾸러기 여자아이 안나. 매년 산타클로스가 오는 날이면\n굉장히 짓궂은 장난을 벌이며, 산타가 선물을 쉽게 배달할 수 없게\n집에 다양한 문제들을 만들어두는걸로 유명하다.\n나는 무려 52년간 단 한번도 배달을 실패한 적 없는 초특급 베테랑.\n한낱 9살 꼬마의 장난 따위에 실패할 내가 아니지!\n썰매 빼와라 루돌프. 휘바휘바~!",
    "recommendation": "가족들과 함께하기에도 괜찮은 테마를 찾으시는 분"
  },
  {
    "id": 72,
    "location": "대구광역시",
    "storeName": "지구별방탈출",
    "address": "대구광역시 중구 동성로 15-1",
    "phoneNumber": "053-214-6277",
    "homepage": "https://지구별.com",
    "image": "https://지구별.com/storage/xUr7fkLyW2BpTzbvBzLP1KQUj1Ud3vPDF0BEWofn.jpg",
    "title": "우리 아빠",
    "genre": "공포",
    "difficulty": 3,
    "activity": 3,
    "horror": 5,
    "description": "어느 날 아빠가 나에게 물었다.\n\n내 딸, 기분이 어떠니?\n\n나는 대답했다.\n\n너무 행복해요 아빠\n\n(이 테마는 자극적이고 불편한 요소가 포함되어 있습니다)",
    "recommendation": "무섭다고 집중력을 잃지 않는 독한 분"
  },
  {
    "id": 73,
    "location": "대구광역시",
    "storeName": "지구별방탈출",
    "address": "대구광역시 중구 동성로 15-1",
    "phoneNumber": "053-214-6277",
    "homepage": "https://지구별.com",
    "image": "https://지구별.com/storage/PzjVklJhqm9uDDDATLbf8jyxyUWpNUliWrfbWvVJ.jpg",
    "title": "펭귄 키우기",
    "genre": "문제방",
    "difficulty": 5,
    "activity": 4,
    "horror": 1,
    "description": "남극 대륙의 지독한 한파 속에서 태어난 작은 펭귄.\n\n당신의 능력과 선택에 따라 달라지는 145개의 결말.\n\n나는 어떤 펭귄이 될까?\n\n※ 문제가 매우 어렵고 아주 많은 문제방입니다.\n※ 이지/하드 중 모드 선택이 가능하며, 하드모드는 100방 이상 매니아들에게 권장합니다",
    "recommendation": "매우 어렵고 매우 많은 문제를 풀고 싶으신 분"
  },
  {
    "id": 74,
    "location": "대구광역시",
    "storeName": "지구별방탈출",
    "address": "대구광역시 중구 동성로 15-1",
    "phoneNumber": "053-214-6277",
    "homepage": "https://지구별.com",
    "image": "https://지구별.com/storage/lJ0K6Tyb2bJFaQPV1rXDydRNqTSe7s6nCK36yCrN.jpg",
    "title": "사명:투쟁의 노래",
    "genre": "탈옥",
    "difficulty": 4,
    "activity": 5,
    "horror": 4,
    "description": "그날의 모든 것은 우리의 선택이었다.\n\n처절하게 울려 퍼졌던 투쟁의 노래.\n사명은 분리 테마입니다.\n*관찰력이 중요한 간수팀과 활동성이 높은 죄수팀으로 나눠집니다.협력과 소통이 중요합니다.",
    "recommendation": "들어는 봤는가 “분리 진행 방식”. 경험해보고 싶으신 분"
  },
  {
    "id": 75,
    "location": "대구광역시",
    "storeName": "코드네임블랙 대구점",
    "address": "대구광역시 중구 동성로 25",
    "phoneNumber": "0507-1332-4466",
    "homepage": "http://www.codenameblack-dg.co.kr/index.html",
    "image": "http://www.codenameblack-dg.co.kr/pimages/Product/Pr_1522733182.jpg",
    "title": "어바웃 타임",
    "genre": "성인",
    "difficulty": 2,
    "activity": 3,
    "horror": 0,
    "description": "",
    "recommendation": "그렇게 야하진 않고 스토리적 요소가 풍부한 방을 찾으시는 분"
  },
  {
    "id": 76,
    "location": "대구광역시",
    "storeName": "코드네임블랙 대구점",
    "address": "대구광역시 중구 동성로 25",
    "phoneNumber": "0507-1332-4466",
    "homepage": "http://www.codenameblack-dg.co.kr/index.html",
    "image": "http://www.codenameblack-dg.co.kr/pimages/Product/Pr_1508405735.jpg",
    "title": "냥이강쥐의 대모험",
    "genre": "코믹",
    "difficulty": 2,
    "activity": 1,
    "horror": 2,
    "description": "",
    "recommendation": "직관적으로 쉽게 풀리는 문제로 입문하고 싶으신 분"
  },
  {
    "id": 77,
    "location": "대구광역시",
    "storeName": "코드네임블랙 대구점",
    "address": "대구광역시 중구 동성로 25",
    "phoneNumber": "0507-1332-4466",
    "homepage": "http://www.codenameblack-dg.co.kr/index.html",
    "image": "http://www.codenameblack-dg.co.kr/pimages/Product/Pr_1508406190.jpg",
    "title": "스카이 테러",
    "genre": "어드벤처",
    "difficulty": 5,
    "activity": 2,
    "horror": 1,
    "description": "",
    "recommendation": "정신 없이 바쁜 방탈출을 즐기시는 분"
  },
  {
    "id": 78,
    "location": "대구광역시",
    "storeName": "코드네임블랙 대구점",
    "address": "대구광역시 중구 동성로 25",
    "phoneNumber": "0507-1332-4466",
    "homepage": "http://www.codenameblack-dg.co.kr/index.html",
    "image": "http://www.codenameblack-dg.co.kr/pimages/Product/Pr_1522733027.jpg",
    "title": "야간자율학습",
    "genre": "공포",
    "difficulty": 3,
    "activity": 2,
    "horror": 4,
    "description": "",
    "recommendation": "샅샅히 뒤져보는 방탈출을 좋아하시는 분"
  },
  {
    "id": 79,
    "location": "대구광역시",
    "storeName": "코드네임블랙 대구점",
    "address": "대구광역시 중구 동성로 25",
    "phoneNumber": "0507-1332-4466",
    "homepage": "http://www.codenameblack-dg.co.kr/index.html",
    "image": "http://www.codenameblack-dg.co.kr/pimages/Product/Pr_1508404613.jpg",
    "title": "스페이스 쉽: 라비린스",
    "genre": "판타지",
    "difficulty": 4,
    "activity": 5,
    "horror": 1,
    "description": "",
    "recommendation": "우주선에서 홀로 깨어났다는 낯선 설정으로 오는 서늘한 느낌을 느끼고 싶으신 분"
  },
  {
    "id": 80,
    "location": "대구광역시",
    "storeName": "코드네임블랙 대구점",
    "address": "대구광역시 중구 동성로 25",
    "phoneNumber": "0507-1332-4466",
    "homepage": "http://www.codenameblack-dg.co.kr/index.html",
    "image": "http://www.codenameblack-dg.co.kr/pimages/Product/Pr_1508405870.jpg",
    "title": "로스트 원더랜드",
    "genre": "스릴러",
    "difficulty": 3,
    "activity": 3,
    "horror": 3,
    "description": "",
    "recommendation": "어두운 분위기의 방에서의 무서움을 즐기시는 분"
  },
  {
    "id": 81,
    "location": "대구광역시",
    "storeName": "코드네임블랙 대구점",
    "address": "대구광역시 중구 동성로 25",
    "phoneNumber": "0507-1332-4466",
    "homepage": "http://www.codenameblack-dg.co.kr/index.html",
    "image": "http://www.codenameblack-dg.co.kr/pimages/Product/Pr_1520491974.jpg",
    "title": "그녀의 오피스텔",
    "genre": "성인/공포",
    "difficulty": 4,
    "activity": 2,
    "horror": 5,
    "description": "",
    "recommendation": "꾸금력이 강한 테마를 좋아하시는 분"
  },
  {
    "id": 82,
    "location": "대구광역시",
    "storeName": "코드네임블랙 대구점",
    "address": "대구광역시 중구 동성로 25",
    "phoneNumber": "0507-1332-4466",
    "homepage": "http://www.codenameblack-dg.co.kr/index.html",
    "image": "http://www.codenameblack-dg.co.kr/pimages/Product/Pr_1522982634.jpg",
    "title": "드워프: 금지된 마법",
    "genre": "판타지",
    "difficulty": 4,
    "activity": 2,
    "horror": 1,
    "description": "",
    "recommendation": "광산은 맞는데 분위기가 정말 좋은… 인테리어 좋은 방을 선호하시는 분"
  },
  {
    "id": 83,
    "location": "대구광역시",
    "storeName": "코드이스케이프 대구점",
    "address": "대구광역시 수성구 달구벌대로 2552",
    "phoneNumber": "0507-1418-0239",
    "homepage": "https://www.code-escape-dg.com:6016/web/home.php?mid=3&go=rooms",
    "image": "https://www.code-escape-dg.com:6016/file/theme/11_a.jpg",
    "title": "프리즌 브레이크",
    "genre": "첩보",
    "difficulty": 4,
    "activity": 3,
    "horror": 3,
    "description": "당신은 은밀하게 활동을 하던 스파이. 활동 중 적에게 정체가 발각되어 감옥에 갇히게 되었다. 1시간뒤, 당신을 구하기 위해 본부에서 헬기를 보내온다. 헬기를 놓치면 당신은 영영 감옥에 갇히게 되는데... 헬기가 떠나기전 1시간 안에 감옥을 탈출하라!",
    "recommendation": "퀄리티 높은 소품과 장식을 원하시는 분"
  },
  {
    "id": 84,
    "location": "대구광역시",
    "storeName": "코드이스케이프 대구점",
    "address": "대구광역시 수성구 달구벌대로 2552",
    "phoneNumber": "0507-1418-0239",
    "homepage": "https://www.code-escape-dg.com:6016/web/home.php?mid=3&go=rooms",
    "image": "https://www.code-escape-dg.com:6016/file/theme/13_a.jpg",
    "title": "게이샤의 붉은 편지",
    "genre": "추격",
    "difficulty": 4,
    "activity": 3,
    "horror": 4,
    "description": "독립운동중 일본군이 쏜 총에 맞아 정신을 잃은 당신, 정신을 차려보니 어느 방안에 당신이 치료되어있다. 일본군의 독립군 소탕작전을 피하기 위해 당신은 동료의 집에 있는 독립군 명단을 확보하고 멀리 도망쳐야 한다. 1시간안에 독립군의 명단을 찾고 이곳을 탈출하라",
    "recommendation": "스토리라인, 컨셉, 인테리어 3박자 모두 갖춘 방을 찾으시는 분"
  },
  {
    "id": 85,
    "location": "대구광역시",
    "storeName": "코드이스케이프 대구점",
    "address": "대구광역시 수성구 달구벌대로 2552",
    "phoneNumber": "0507-1418-0239",
    "homepage": "https://www.code-escape-dg.com:6016/web/home.php?mid=3&go=rooms",
    "image": "https://www.code-escape-dg.com:6016/file/theme/14_a.jpg",
    "title": "바이러스",
    "genre": "바이러스",
    "difficulty": 4,
    "activity": 3,
    "horror": 3,
    "description": "에너지부족 해결을 위한 원자력 발전소의 핵폐기물 문제로 전세계가 돌연변이 바이러스에 물들었다. 당신은 돌연변이 바이러스 백신을 개발한 Greg박사의 연구실에 찾아갔지만 그곳또한 돌연변이에 의해 점령되어 당신의 침입을 느낀 돌연변이들은 1시간 타이머가 달린 폭탄을 작동시키고 연구실을 폐쇄했다. 1시간안에 백신을 찾고 그곳을 탈출하라!",
    "recommendation": "방탈출을 처음 도전하시는 분"
  },
  {
    "id": 86,
    "location": "대구광역시",
    "storeName": "코드이스케이프 대구점",
    "address": "대구광역시 수성구 달구벌대로 2552",
    "phoneNumber": "0507-1418-0239",
    "homepage": "https://www.code-escape-dg.com:6016/web/home.php?mid=3&go=rooms",
    "image": "https://www.code-escape-dg.com:6016/file/theme/15_a.jpg",
    "title": "키드냅",
    "genre": "스릴러",
    "difficulty": 5,
    "activity": 3,
    "horror": 3,
    "description": "경찰인 당신. 당신의 친구가 납치되었다는 소식을 듣고 범인의 집으로 진입하여 범인을 사살했다. 그러나 당신의 친구는 1시간 뒤에 장기매매업자들에게 교환될거라는 메모가 남겨져 있고 범인의 덫에 걸려 침입한 순간 모든 문은 잠겨버렸다. 1시간안에 이곳을 탈출하여 당신의 친구를 구하라!",
    "recommendation": "어려운 거 잘 푸시는 분"
  },
  {
    "id": 87,
    "location": "대구광역시",
    "storeName": "코드이스케이프 대구점",
    "address": "대구광역시 수성구 달구벌대로 2552",
    "phoneNumber": "0507-1418-0239",
    "homepage": "https://www.code-escape-dg.com:6016/web/home.php?mid=3&go=rooms",
    "image": "https://www.code-escape-dg.com:6016/file/theme/12_a.jpg",
    "title": "의문의 시선: 추격",
    "genre": "스릴러",
    "difficulty": 5,
    "activity": 4,
    "horror": 4,
    "description": "연쇄적으로 이어져 왔었던 의문의 차량사고..당신이 이 범행의 피해자가 될 줄은 몰랐다. 아무도 밝히지 못했던 범인의 범행 동기를 당신이 찾아야만 한다. 1시간 후 더 큰 위험이 닥치기 전 이곳을 탈출하라!",
    "recommendation": "점점 공포스러워지는 분위기에 긴장감 가득 플레이 하고 싶으신 분"
  },
  {
    "id": 88,
    "location": "대구광역시",
    "storeName": "황금열쇠 동성로점",
    "address": "대구광역시 중구 동성로2길 18-12",
    "phoneNumber": "053-428-0045",
    "homepage": "http://황금열쇠.com/layout/res/home.php?go=main",
    "image": "http://황금열쇠.com/file/theme/2_a.jpg",
    "title": "X됐다",
    "genre": "코믹",
    "difficulty": 2,
    "activity": 3,
    "horror": 1,
    "description": "아.. X됐다",
    "recommendation": "실제로 문제 풀면서 X됐다를 느끼고 싶으신 분"
  },
  {
    "id": 89,
    "location": "대구광역시",
    "storeName": "황금열쇠 동성로점",
    "address": "대구광역시 중구 동성로2길 18-12",
    "phoneNumber": "053-428-0045",
    "homepage": "http://황금열쇠.com/layout/res/home.php?go=main",
    "image": "http://황금열쇠.com/file/theme/3_a.jpg",
    "title": "JAIL.O",
    "genre": "미션",
    "difficulty": 5,
    "activity": 5,
    "horror": 2,
    "description": "최대규모의 감옥, OSPIREAN (추천 4인이상)",
    "recommendation": "또 나오고 또 나오는 방. 스케일이 큰 테마를 좋아하시는 분"
  },
  {
    "id": 90,
    "location": "대구광역시",
    "storeName": "황금열쇠 동성로점",
    "address": "대구광역시 중구 동성로2길 18-12",
    "phoneNumber": "053-428-0045",
    "homepage": "http://황금열쇠.com/layout/res/home.php?go=main",
    "image": "http://황금열쇠.com/file/theme/1_a.jpg",
    "title": "가이아 기적의 땅",
    "genre": "판타지",
    "difficulty": 3,
    "activity": 3,
    "horror": 2,
    "description": "모든 것이 이 곳에서 시작된다.",
    "recommendation": "신비로운 스토리에 색다른 몰입감을 즐기시는 분"
  },
  {
    "id": 91,
    "location": "대구광역시",
    "storeName": "황금열쇠 동성로점",
    "address": "대구광역시 중구 동성로2길 18-12",
    "phoneNumber": "053-428-0045",
    "homepage": "http://황금열쇠.com/layout/res/home.php?go=main",
    "image": "http://황금열쇠.com/file/theme/5_a.jpg",
    "title": "타임 스틸러",
    "genre": "어드벤처",
    "difficulty": 4,
    "activity": 4,
    "horror": 2,
    "description": "시간의저택 으로 초대합니다 (추천 3인이상)",
    "recommendation": "달리기 테마. 엄청 높은 활동성에 땀 좀 흘리고 싶으신 분"
  },
  {
    "id": 92,
    "location": "포항시",
    "storeName": "더와이 방탈출카페",
    "address": "경북 포항시 북구 중앙상가4길 15",
    "phoneNumber": "054-610-2030",
    "homepage": "https://blog.naver.com/theyescape",
    "image": "https://search.pstatic.net/common/?autoRotate=true&quality=95&type=w750&src=https%3A%2F%2Fldb-phinf.pstatic.net%2F20161007_172%2F1475799670453CuAdA_JPEG%2F176880618076414_6.jpeg",
    "title": "Christmas",
    "genre": "코믹",
    "difficulty": 4,
    "activity": 3,
    "horror": 0,
    "description": "오늘은 크리스마스 이브, 설레는 마음으로 선물을 포장하는 당신은 산타클로스다. 소중한 선물의 전달을 시작하고자 벽난로를 통해 첫 번째 집에 들어갔다. 조용히 선물을 두고 돌아가려는 순간, 굴뚝이 벽으로 막혀 버린 것을 발견한 산타! 전세계 어린이들이 기다리고 있고, 이제 시간은 얼마 없다. 차가운 공기로 뒤덮여버린 이 집을 반드시 탈출해야만 한다.",
    "recommendation": "365일 크리스마스를 느끼고 싶은 분"
  },
  {
    "id": 93,
    "location": "포항시",
    "storeName": "더와이 방탈출카페",
    "address": "경북 포항시 북구 중앙상가4길 16",
    "phoneNumber": "054-610-2030",
    "homepage": "https://blog.naver.com/theyescape",
    "image": "https://search.pstatic.net/common/?autoRotate=true&quality=95&type=w750&src=https%3A%2F%2Fldb-phinf.pstatic.net%2F20161007_183%2F1475799670398EyOql_JPEG%2F176880618076414_5.jpeg",
    "title": "Anti Science",
    "genre": "SF",
    "difficulty": 3,
    "activity": 3,
    "horror": 2,
    "description": "당신은 인공지능 연구소장, 오래전 사고로 가족을 잃고 AI강아지 '네모'를 가족 삼아 지냈다. 그런데 어느날 강아지 '네모'가 실종되었다. AI에 반대하는 테러조직 Anti - Science의 납치가 유력하다. 조직의 본거지에 침투하여 '네모'를 되찾기로 결심한 당신! 과연 무사히 구출할 수 있을 것인가?",
    "recommendation": "전자장비를 이용해 문제를 풀고 싶으신 분, SF물을 좋아하시는 분"
  },
  {
    "id": 94,
    "location": "포항시",
    "storeName": "더와이 방탈출카페",
    "address": "경북 포항시 북구 중앙상가4길 17",
    "phoneNumber": "054-610-2030",
    "homepage": "https://blog.naver.com/theyescape",
    "image": "https://search.pstatic.net/common/?autoRotate=true&quality=95&type=w750&src=https%3A%2F%2Fldb-phinf.pstatic.net%2F20161007_200%2F1475799670353tgRoY_JPEG%2F176880618076414_4.jpeg",
    "title": "Forgotton Kingdom",
    "genre": "스릴러",
    "difficulty": 2,
    "activity": 3,
    "horror": 3,
    "description": "당신은 완전히 잊혀진 왕조의 마지막 혈통이다. 반역에 의해 불타버린 궁전에 왕궁의 상징이 비밀스럽게 숨겨지고, 마지막 왕족인 당신은 한 치를 알 수 없는 이 곳에 발을 내딛는다.",
    "recommendation": "방탈출을 처음 해보시는 분. 중세 시대 인테리어를 느끼고 싶은 분. 왕자님,공주님이 되어보고 싶은 분."
  },
  {
    "id": 95,
    "location": "포항시",
    "storeName": "더와이 방탈출카페",
    "address": "경북 포항시 북구 중앙상가4길 18",
    "phoneNumber": "054-610-2030",
    "homepage": "https://blog.naver.com/theyescape",
    "image": "https://search.pstatic.net/common/?autoRotate=true&quality=95&type=w750&src=https%3A%2F%2Fldb-phinf.pstatic.net%2F20161007_192%2F1475799670274hg12s_JPEG%2F176880618076414_3.jpeg",
    "title": "Time Traveling",
    "genre": "판타지",
    "difficulty": 3,
    "activity": 3,
    "horror": 2,
    "description": "새해 첫 날, 레스토랑에서 식사 도중 그녀의 심기가 많이 불편해 보인다. 영문을 모르고 어떻게든 달래보려 노력했지만, 돌아오는 한 마디. 오빠가 뭘 잘못했는지 아직도 모르겠어? 섭섭함에 치밀어 오는 화를 고르고 다시 그녀를 올려보는 순간! 레스토랑은 온데간데 없어지고 그녀를 처음봤던 유럽 골목길에 홀로 앉은 당신을 발견하는데...",
    "recommendation": "로맨틱한 분위기의 데이트를 찾으시는 분. 탄탄한 스토리를 원하시는 분. 판타지 로맨스를 좋아하시는 분."
  },
  {
    "id": 96,
    "location": "포항시",
    "storeName": "더와이 방탈출카페",
    "address": "경북 포항시 북구 중앙상가4길 19",
    "phoneNumber": "054-610-2030",
    "homepage": "https://blog.naver.com/theyescape",
    "image": "https://search.pstatic.net/common/?autoRotate=true&quality=95&type=w750&src=https%3A%2F%2Fldb-phinf.pstatic.net%2F20161007_152%2F1475799670234AFDSW_JPEG%2F176880618076414_2.jpeg",
    "title": "Deep Forest",
    "genre": "어드벤처",
    "difficulty": 5,
    "activity": 4,
    "horror": 2,
    "description": "당신은 고대 문명을 찾아 세계를 여행하는 고고학자이다. 새로운 유적을 찾아 정글을 헤매던 중, 알쑤 없는 수수께끼를 만나게 된다. 분명 오래토록 황폐했던 곳인데. 당신을 부르는 이 이정표들을 누구의 것일까.",
    "recommendation": "모험심이 있는 분. 색다른 인테리어를 원하시는 분. 어드벤처 영화를 좋아하시는 분."
  },
  {
    "id": 97,
    "location": "포항시",
    "storeName": "룸즈에이 포항점",
    "address": "경북 포항시 북구 중앙로 273",
    "phoneNumber": "054-610-2030",
    "homepage": "http://roomsa.co.kr/new_main.asp?R_JIJEM=S11",
    "image": "https://search.pstatic.net/common/?autoRotate=true&quality=95&type=w750&src=https%3A%2F%2Fldb-phinf.pstatic.net%2F20191206_119%2F1575624040234aCTzj_JPEG%2Fz2t9cEjJ_Iy02C-6EIwa2UbS.jpg",
    "title": "너와 나의 이야기",
    "genre": "감성/스토리",
    "difficulty": 3,
    "activity": 3,
    "horror": 0,
    "description": "너와 처음 만난 건, 달과 가장 가까운 골목길이었다. 박스 안에서 힘겹게 울음소리를 내던 네 모습을 아직 나는 기억한다. 이것은 너와의 처음부터 마지막까지를 다룬, 10년 동안의 이야기이다.",
    "recommendation": "감성 테마를 좋아하시는 분. 스토리를 중시하시는 분"
  },
  {
    "id": 98,
    "location": "포항시",
    "storeName": "룸즈에이 포항점",
    "address": "경북 포항시 북구 중앙로 273",
    "phoneNumber": "054-610-2030",
    "homepage": "http://roomsa.co.kr/new_main.asp?R_JIJEM=S11",
    "image": "https://search.pstatic.net/common/?autoRotate=true&quality=95&type=w750&src=https%3A%2F%2Fldb-phinf.pstatic.net%2F20191206_259%2F1575624048756YxKX5_JPEG%2FmcO8nXKFW9lZJDbHJyd_ZXRR.jpg",
    "title": "안개꽃",
    "genre": "감성/로맨스",
    "difficulty": 4,
    "activity": 2,
    "horror": 0,
    "description": "화가인 그가 내게서 떠나간지 어느덧 한 달, 나는 여전히 그와의 시간 속에 머물러 있다. 그리움과 원망을 가득 안고 골목길을 걷던 어느 날, 밤공기를 들이마시며 한 걸음씩 내딛던 나는 작은 골목길과는 어울리지 않는 전시관을 보게 되었다. 처음 보는 전시관이었지만 어디선가 그의 향기가 흘러나오는 듯 했고, 그 추억 속의 향기에 이끌려 전시회장 안으로 들어서게 되었다.",
    "recommendation": "감동적인 테마를 좋아하시는 분."
  },
  {
    "id": 99,
    "location": "포항시",
    "storeName": "룸즈에이 포항점",
    "address": "경북 포항시 북구 중앙로 273",
    "phoneNumber": "054-610-2030",
    "homepage": "http://roomsa.co.kr/new_main.asp?R_JIJEM=S11",
    "image": "https://search.pstatic.net/common/?autoRotate=true&quality=95&type=w750&src=https%3A%2F%2Fldb-phinf.pstatic.net%2F20191206_151%2F157562405260317MEh_JPEG%2F3EdS_JoxX8DDnSpdiq3PUeNu.jpg",
    "title": "시크릿 에이전트",
    "genre": "잠입/수사",
    "difficulty": 4,
    "activity": 4,
    "horror": 1,
    "description": "카디프에 위치해 있는 비밀안가. 양복점으로 운영 중이던 이곳이 적대 세력에 의해 공격 당하고 이곳을 관리하던 관리인 Merlin은 혼수 상태에 빠져버린다. 이 곳 어딘가에 일급 기밀 CD를 보관하는 장소가 있지만, 유일하게 비밀장소를 알고 있던 Merlin이 의식이 없기 때문에 요원들을 파견 하게 되는데... 일급 문서가 있는 CD를 찾아 사수하라!",
    "recommendation": "모험을 좋아하시는 분. 킹스맨 영화를 재미있게 보신 분"
  },
  {
    "id": 100,
    "location": "포항시",
    "storeName": "더패닉 방탈출카페",
    "address": "경북 포항시 북구 중앙상가길 2",
    "phoneNumber": "054-255-1583",
    "homepage": "http://thepanic.modoo.at/",
    "image": "https://modo-phinf.pstatic.net/20161112_199/1478937087195PPN87_JPEG/mosaKpB9Lh.jpeg?type=a1100",
    "title": "생존의 기로 1",
    "genre": "스릴러",
    "difficulty": 3,
    "activity": 4,
    "horror": 4,
    "description": "2005년3월... 미국 전역은 헬로우맨으로 인해 공포로 휩싸인다.매주 사망자가 쏟아져 나왔고, 살해현장에는 여지없이 노란색 락카로 칠해진 HELLO란 문구가 선명히 남아있었다.그리고 오늘, 두명의 프로겜블러를 대상으로 또 다른 살인이 시작된다.",
    "recommendation": "스릴러를 좋아하시는 분"
  },
  {
    "id": 101,
    "location": "포항시",
    "storeName": "더패닉 방탈출카페",
    "address": "경북 포항시 북구 중앙상가길 2",
    "phoneNumber": "054-255-1583",
    "homepage": "http://thepanic.modoo.at/",
    "image": "https://modo-phinf.pstatic.net/20161112_51/1478937408874vg51o_JPEG/mosaIVhKMt.jpeg?type=a1100",
    "title": "센의 진실",
    "genre": "공포",
    "difficulty": 4,
    "activity": 3,
    "horror": 5,
    "description": "산골마을의 한적한 밤, 하늘일 뚫린 듯 쏟아지는 소나기를 헤치며 한 소녀가 걷고 있다. 긴 시간을 걸었는지, 흠뻑 젖은 옷과 축 처진 머리카락... 그 뒤를 다른 소녀들이 뒤따르고 있었고, 초점을 잃은 소녀의 눈동자는 골목 끝 의료원을 바라보는데...",
    "recommendation": "강심장을 가지신 분"
  },
  {
    "id": 102,
    "location": "포항시",
    "storeName": "더패닉 방탈출카페",
    "address": "경북 포항시 북구 중앙상가길 2",
    "phoneNumber": "054-255-1583",
    "homepage": "http://thepanic.modoo.at/",
    "image": "https://modo-phinf.pstatic.net/20161112_2/1478937917638oeVKX_JPEG/mosag0pzam.jpeg?type=a1100",
    "title": "흉가탈출",
    "genre": "공포",
    "difficulty": 5,
    "activity": 3,
    "horror": 4,
    "description": "아무도 살지 않는 깊은 산속의 흉가... 15년전 일어난 화재사건으로 한 가족이 한줌의 재가 되었고, 억울함에 떠나지 못하는 한 여인의 울음소리가 매일같이 울려 퍼지는데...",
    "recommendation": "강심장을 가지신 분"
  },
  {
    "id": 103,
    "location": "포항시",
    "storeName": "더패닉 방탈출카페",
    "address": "경북 포항시 북구 중앙상가길 2",
    "phoneNumber": "054-255-1583",
    "homepage": "http://thepanic.modoo.at/",
    "image": "https://modo-phinf.pstatic.net/20161112_217/1478939410662v8OsO_JPEG/mosa7WSwON.jpeg?type=a1100",
    "title": "제물",
    "genre": "공포",
    "difficulty": 4,
    "activity": 3,
    "horror": 4,
    "description": "파리지하의 조그마한 바에서 술을 즐기던 두 남자 몽환적 표정의 바텐더가 넘기는 한잔의 술에 그들의 운명이 이리도 바뀔줄은 몰랐다. 눈앞에는 애기로만 들었던 베인교의 상징이 그려져 있었고 언제 그들이 제물이 될지도 모른 채 긴장감은 더해져 가는데...",
    "recommendation": "미스터리를 좋아하시는 분"
  },
  {
    "id": 104,
    "location": "포항시",
    "storeName": "더패닉 방탈출카페",
    "address": "경북 포항시 북구 중앙상가길 2",
    "phoneNumber": "054-255-1583",
    "homepage": "http://thepanic.modoo.at/",
    "image": "https://modo-phinf.pstatic.net/20161112_42/1478939473504EbKLn_JPEG/mosar2DzcP.jpeg?type=a1100",
    "title": "파괴된도시 1",
    "genre": "스릴러",
    "difficulty": 4,
    "activity": 3,
    "horror": 4,
    "description": "피의 냄새만을 찾아 날뛰는 브리처들의 공격으로 폐허가 되버린 마을거리에서 두 개의 작은 그림자가 내달리고 있다. 그 뒤로 점차 늘어나는 브리처무리... 더 이상 도망갈 여력을 잃어 버린 그림자들은 막다른 길에 세워진 컨테이너 건물로 들어가 문을 걸어 잠그는데...",
    "recommendation": "스릴러를 좋아하시는 분"
  },
  {
    "id": 105,
    "location": "포항시",
    "storeName": "더패닉 방탈출카페",
    "address": "경북 포항시 북구 중앙상가길 2",
    "phoneNumber": "054-255-1583",
    "homepage": "http://thepanic.modoo.at/",
    "image": "https://modo-phinf.pstatic.net/20161112_250/1478939538786dmLmN_JPEG/mosaDmeZG9.jpeg?type=a1100",
    "title": "스파이",
    "genre": "스릴러",
    "difficulty": 4,
    "activity": 2,
    "horror": 3,
    "description": "건장한 군인들이 포로를 이끌고 복도 끝 고문실로 향한다. 이내 방안에 울려펴지는 고문소리와 신음소리... 얼마 뒤 고문에 별소득이 없었는지 투덜거리며 나오는 군인들 그리고 이를 기다렸다는 듯, 스파이 알프레드가 눈을 뜨는데...",
    "recommendation": "스파이를 좋아하시는 분"
  },
  {
    "id": 106,
    "location": "포항시",
    "storeName": "더패닉 방탈출카페",
    "address": "경북 포항시 북구 중앙상가길 2",
    "phoneNumber": "054-255-1583",
    "homepage": "http://thepanic.modoo.at/",
    "image": "https://modo-phinf.pstatic.net/20161112_237/1478939611842Lnu5F_JPEG/mosa124EDd.jpeg?type=a1100",
    "title": "피의 멜로디",
    "genre": "스릴러",
    "difficulty": 4,
    "activity": 2,
    "horror": 3,
    "description": "어두운 방안… 정신을 잃은 듯 보이는 사람들이 차곡차곡 쌓여가고 이를 흐뭇하게 바라보는 한 남자. 남자가 방을 나선지 얼마나 되었을까? 방에서는 하나 둘 깨어난 사람들이 깨어나고 방문 밖에는뱀파이어들에게 당하는 이들의 비명으로 가득한데…",
    "recommendation": "뱀파이어를 좋아하시는 분"
  },
  {
    "id": 107,
    "location": "포항시",
    "storeName": "더패닉 방탈출카페",
    "address": "경북 포항시 북구 중앙상가길 2",
    "phoneNumber": "054-255-1583",
    "homepage": "http://thepanic.modoo.at/",
    "image": "https://modo-phinf.pstatic.net/20161112_222/1478939666367mKdbP_JPEG/mosaZbXUKs.jpeg?type=a1100",
    "title": "히말라야",
    "genre": "감성",
    "difficulty": 4,
    "activity": 2,
    "horror": 3,
    "description": "아들의 수술비 마련을위해 마지막 등반을 결정한 라울과 팀원들 하지만 히말라야 칸첸중가는 그들의 입성을 허락하지 않고... 팀원들의 안전을 위해 라울은 더 이상의 진행을 멈추려 하지만 친구 피어스는 이를 반대하며, 라울을 베이스캠프에 가두기에 이르는데...",
    "recommendation": "스토리를 중요하게 보시는 분"
  },
  {
    "id": 108,
    "location": "포항시",
    "storeName": "더패닉 방탈출카페",
    "address": "경북 포항시 북구 중앙상가길 2",
    "phoneNumber": "054-255-1583",
    "homepage": "http://thepanic.modoo.at/",
    "image": "https://modo-phinf.pstatic.net/20161112_17/1478939726702otLkd_JPEG/mosaRR0aRE.jpeg?type=a1100",
    "title": "생존의 기로 2",
    "genre": "미스터리/스릴러",
    "difficulty": 5,
    "activity": 3,
    "horror": 4,
    "description": "미국 전역을 공포로 몰아갔던 헬로우맨! 그가 이제 런던에 나타났다. 아무도 없는 폐쇄철로에 지하철이 멈추고, 그 안에서 울먹이며 소리치는 사람들의 목소리가 가득한데...",
    "recommendation": "미스터리 공포물을 좋아하시는 분"
  },
  {
    "id": 109,
    "location": "경주시",
    "storeName": "더코드 경주점",
    "address": "경북 경주시 원효로 122",
    "phoneNumber": "054-771-9502",
    "homepage": "http://thecode02.kr",
    "image": "http://thecode02.kr/data/goodsImages/GOODS1_20220504174904.jpg",
    "title": "박물관: 도둑들",
    "genre": "첩보",
    "difficulty": 4,
    "activity": 4,
    "horror": 3,
    "description": "어느 한적한 상가 안 우연히 지나가던 이웃이 발견한 여자는 \n두 손이 뒤로 묶인 채 눈이 가려져 있었다. \n마지막 피해자이자, 유일한 목격자인 그녀. \n최면을 통해 그날의 범인을 기억해내라",
    "recommendation": "영화를 좋아하는 분"
  },
  {
    "id": 110,
    "location": "경주시",
    "storeName": "더코드 경주점",
    "address": "경북 경주시 원효로 122",
    "phoneNumber": "054-771-9502",
    "homepage": "http://thecode03.kr",
    "image": "http://thecode02.kr/data/goodsImages/GOODS1_20220504173308.jpg",
    "title": "최부장의 비밀",
    "genre": "수사",
    "difficulty": 4,
    "activity": 3,
    "horror": 3,
    "description": "조세 5국 열혈 공무원 황 팀장. 불의를 보면 참지 못하는 그는 \n뛰어난 직감과 끈질긴 성격을 바탕으로 조세국의 최연소 팀장.\n어느 날 익명의 제보자에게 걸어온 전화. \n제보자는 믿고 따르는 최 부장의 비리를 고발하는데…",
    "recommendation": "회사 스트레스가 많으신 분"
  },
  {
    "id": 111,
    "location": "경주시",
    "storeName": "더코드 경주점",
    "address": "경북 경주시 원효로 122",
    "phoneNumber": "054-771-9502",
    "homepage": "http://thecode04.kr",
    "image": "http://thecode02.kr/data/goodsImages/GOODS1_20220504172105.jpg",
    "title": "몽타주: 강력 1반",
    "genre": "수사",
    "difficulty": 4,
    "activity": 3,
    "horror": 4,
    "description": "어느 한적한 상가 안 우연히 지나가던 이웃이 발견한 여자는 \n두 손이 뒤로 묶인 채 눈이 가려져 있었다. \n마지막 피해자이자, 유일한 목격자인 그녀. \n최면을 통해 그날의 범인을 기억해내라",
    "recommendation": "경찰이 되어보고 싶으신 분"
  },
  {
    "id": 112,
    "location": "경주시",
    "storeName": "더코드 경주점",
    "address": "경북 경주시 원효로 122",
    "phoneNumber": "054-771-9502",
    "homepage": "http://thecode05.kr",
    "image": "http://thecode02.kr/data/goodsImages/GOODS1_20220504175951.jpg",
    "title": "도박꾼: 마지막 배팅",
    "genre": "범죄",
    "difficulty": 5,
    "activity": 4,
    "horror": 3,
    "description": "지극히 평범한 회사원, 그리고 졸업은 앞둔 대학생으로 살고 있는 그들은 수년 전\n전국 도박판을 휩쓴 전문도박팀.\n2년 전 인천에서의 화투판을 마지막으로 그들은 도박판을 영원히 떠나기로 다 같이 약속한다.\n어느 날 걸려온 전화... 연락이 되지 않던 친구가 도박판에 감금됐는다는 소식을 전해 듣게 되고\n그들은 친구를 구하기 위해 다시 뭉치게 된다.",
    "recommendation": "타짜 영화를 재미있게 보신 분"
  }
]
